{"summaries":[{"symbol":{"__symbol":0,"members":[]},"metadata":{"__symbolic":"class"},"type":{"summaryKind":2,"type":{"reference":{"__symbol":0,"members":[]},"diDeps":[],"lifecycleHooks":[]},"entryComponents":[{"componentType":{"__symbol":1,"members":[]},"componentFactory":{"__symbol":2,"members":[]}},{"componentType":{"__symbol":3,"members":[]},"componentFactory":{"__symbol":4,"members":[]}},{"componentType":{"__symbol":5,"members":[]},"componentFactory":{"__symbol":6,"members":[]}}],"providers":[{"provider":{"token":{"identifier":{"reference":{"__symbol":7,"members":[]}}},"useClass":null,"useFactory":{"reference":{"__symbol":8,"members":[]},"diDeps":[{"isAttribute":false,"isHost":false,"isSelf":false,"isSkipSelf":false,"isOptional":false,"token":{"identifier":{"reference":{"__symbol":9,"members":[]}}}},{"isAttribute":false,"isHost":false,"isSelf":false,"isSkipSelf":false,"isOptional":false,"token":{"identifier":{"reference":{"__symbol":10,"members":[]}}}}]},"deps":[{"isAttribute":false,"isHost":false,"isSelf":false,"isSkipSelf":false,"isOptional":false,"token":{"identifier":{"reference":{"__symbol":9,"members":[]}}}},{"isAttribute":false,"isHost":false,"isSelf":false,"isSkipSelf":false,"isOptional":false,"token":{"identifier":{"reference":{"__symbol":10,"members":[]}}}}],"multi":false},"module":{"reference":{"__symbol":11,"members":[]},"diDeps":[],"lifecycleHooks":[]}},{"provider":{"token":{"identifier":{"reference":{"__symbol":12,"members":[]},"diDeps":[],"lifecycleHooks":[]}},"useClass":{"reference":{"__symbol":12,"members":[]},"diDeps":[],"lifecycleHooks":[]},"useFactory":null,"deps":[],"multi":false},"module":{"reference":{"__symbol":11,"members":[]},"diDeps":[],"lifecycleHooks":[]}},{"provider":{"token":{"identifier":{"reference":{"__symbol":10,"members":[]}}},"useClass":{"reference":{"__symbol":13,"members":[]},"diDeps":[],"lifecycleHooks":[]},"useFactory":null,"deps":[],"multi":false},"module":{"reference":{"__symbol":11,"members":[]},"diDeps":[],"lifecycleHooks":[]}},{"provider":{"token":{"identifier":{"reference":{"__symbol":14,"members":[]}}},"useClass":{"reference":{"__symbol":15,"members":[]},"diDeps":[],"lifecycleHooks":[]},"useFactory":null,"deps":[],"multi":false},"module":{"reference":{"__symbol":11,"members":[]},"diDeps":[],"lifecycleHooks":[]}},{"provider":{"token":{"identifier":{"reference":{"__symbol":9,"members":[]},"diDeps":[{"isAttribute":false,"isHost":false,"isSelf":false,"isSkipSelf":false,"isOptional":false,"token":{"identifier":{"reference":{"__symbol":12,"members":[]}}}},{"isAttribute":false,"isHost":false,"isSelf":false,"isSkipSelf":false,"isOptional":false,"token":{"identifier":{"reference":{"__symbol":14,"members":[]}}}},{"isAttribute":false,"isHost":false,"isSelf":false,"isSkipSelf":false,"isOptional":false,"token":{"identifier":{"reference":{"__symbol":16,"members":[]}}}}],"lifecycleHooks":[]}},"useClass":{"reference":{"__symbol":9,"members":[]},"diDeps":[{"isAttribute":false,"isHost":false,"isSelf":false,"isSkipSelf":false,"isOptional":false,"token":{"identifier":{"reference":{"__symbol":12,"members":[]}}}},{"isAttribute":false,"isHost":false,"isSelf":false,"isSkipSelf":false,"isOptional":false,"token":{"identifier":{"reference":{"__symbol":14,"members":[]}}}},{"isAttribute":false,"isHost":false,"isSelf":false,"isSkipSelf":false,"isOptional":false,"token":{"identifier":{"reference":{"__symbol":16,"members":[]}}}}],"lifecycleHooks":[]},"useFactory":null,"deps":[{"isAttribute":false,"isHost":false,"isSelf":false,"isSkipSelf":false,"isOptional":false,"token":{"identifier":{"reference":{"__symbol":12,"members":[]}}}},{"isAttribute":false,"isHost":false,"isSelf":false,"isSkipSelf":false,"isOptional":false,"token":{"identifier":{"reference":{"__symbol":14,"members":[]}}}},{"isAttribute":false,"isHost":false,"isSelf":false,"isSkipSelf":false,"isOptional":false,"token":{"identifier":{"reference":{"__symbol":16,"members":[]}}}}],"multi":false},"module":{"reference":{"__symbol":11,"members":[]},"diDeps":[],"lifecycleHooks":[]}},{"provider":{"token":{"identifier":{"reference":{"__symbol":16,"members":[]}}},"useClass":null,"useFactory":{"reference":{"__symbol":17,"members":[]},"diDeps":[]},"deps":[],"multi":false},"module":{"reference":{"__symbol":11,"members":[]},"diDeps":[],"lifecycleHooks":[]}},{"provider":{"token":{"identifier":{"reference":{"__symbol":18,"members":[]},"diDeps":[{"isAttribute":false,"isHost":false,"isSelf":false,"isSkipSelf":false,"isOptional":false,"token":{"identifier":{"reference":{"__symbol":7,"members":[]}}}},{"isAttribute":false,"isHost":false,"isSelf":false,"isSkipSelf":false,"isOptional":false,"token":{"identifier":{"reference":{"__symbol":19,"members":[]}}}}],"lifecycleHooks":[]}},"useClass":{"reference":{"__symbol":18,"members":[]},"diDeps":[{"isAttribute":false,"isHost":false,"isSelf":false,"isSkipSelf":false,"isOptional":false,"token":{"identifier":{"reference":{"__symbol":7,"members":[]}}}},{"isAttribute":false,"isHost":false,"isSelf":false,"isSkipSelf":false,"isOptional":false,"token":{"identifier":{"reference":{"__symbol":19,"members":[]}}}}],"lifecycleHooks":[]},"useFactory":null,"deps":[{"isAttribute":false,"isHost":false,"isSelf":false,"isSkipSelf":false,"isOptional":false,"token":{"identifier":{"reference":{"__symbol":7,"members":[]}}}},{"isAttribute":false,"isHost":false,"isSelf":false,"isSkipSelf":false,"isOptional":false,"token":{"identifier":{"reference":{"__symbol":19,"members":[]}}}}],"multi":false},"module":{"reference":{"__symbol":20,"members":[]},"diDeps":[],"lifecycleHooks":[]}},{"provider":{"token":{"identifier":{"reference":{"__symbol":21,"members":[]}}},"useClass":{"reference":{"__symbol":22,"members":[]},"diDeps":[{"isAttribute":false,"isHost":false,"isSelf":false,"isSkipSelf":false,"isOptional":false,"token":{"identifier":{"reference":{"__symbol":23,"members":[]}}}}],"lifecycleHooks":[]},"useFactory":null,"deps":[{"isAttribute":false,"isHost":false,"isSelf":false,"isSkipSelf":false,"isOptional":false,"token":{"identifier":{"reference":{"__symbol":23,"members":[]}}}}],"multi":false},"module":{"reference":{"__symbol":24,"members":[]},"diDeps":[],"lifecycleHooks":[]}},{"provider":{"token":{"identifier":{"reference":{"__symbol":25,"members":[]},"diDeps":[{"isAttribute":false,"isHost":false,"isSelf":false,"isSkipSelf":false,"isOptional":false,"token":{"identifier":{"reference":{"__symbol":26,"members":[]}}}}],"lifecycleHooks":[]}},"useClass":{"reference":{"__symbol":25,"members":[]},"diDeps":[{"isAttribute":false,"isHost":false,"isSelf":false,"isSkipSelf":false,"isOptional":false,"token":{"identifier":{"reference":{"__symbol":26,"members":[]}}}}],"lifecycleHooks":[]},"useFactory":null,"deps":[{"isAttribute":false,"isHost":false,"isSelf":false,"isSkipSelf":false,"isOptional":false,"token":{"identifier":{"reference":{"__symbol":26,"members":[]}}}}],"multi":false},"module":{"reference":{"__symbol":0,"members":[]},"diDeps":[],"lifecycleHooks":[]}},{"provider":{"token":{"identifier":{"reference":{"__symbol":27,"members":[]}}},"useClass":{"reference":{"__symbol":28,"members":[]},"diDeps":[],"lifecycleHooks":[]},"useFactory":null,"deps":[],"multi":false},"module":{"reference":{"__symbol":0,"members":[]},"diDeps":[],"lifecycleHooks":[]}},{"provider":{"token":{"identifier":{"reference":{"__symbol":29,"members":[]}}},"useClass":null,"useFactory":{"reference":{"__symbol":30,"members":[]},"diDeps":[{"isAttribute":false,"isHost":false,"isSelf":false,"isSkipSelf":false,"isOptional":false,"token":{"identifier":{"reference":{"__symbol":31,"members":[]}}}},{"isAttribute":false,"isHost":false,"isSelf":false,"isSkipSelf":false,"isOptional":false,"token":{"identifier":{"reference":{"__symbol":27,"members":[]}}}},{"isAttribute":false,"isHost":false,"isSelf":false,"isSkipSelf":false,"isOptional":false,"token":{"identifier":{"reference":{"__symbol":32,"members":[]}}}},{"isAttribute":false,"isHost":false,"isSelf":false,"isSkipSelf":false,"isOptional":false,"token":{"identifier":{"reference":{"__symbol":25,"members":[]}}}},{"isAttribute":false,"isHost":false,"isSelf":false,"isSkipSelf":false,"isOptional":false,"token":{"identifier":{"reference":{"__symbol":33,"members":[]}}}},{"isAttribute":false,"isHost":false,"isSelf":false,"isSkipSelf":false,"isOptional":false,"token":{"identifier":{"reference":{"__symbol":34,"members":[]}}}},{"isAttribute":false,"isHost":false,"isSelf":false,"isSkipSelf":false,"isOptional":false,"token":{"identifier":{"reference":{"__symbol":35,"members":[]}}}},{"isAttribute":false,"isHost":false,"isSelf":false,"isSkipSelf":false,"isOptional":false,"token":{"identifier":{"reference":{"__symbol":36,"members":[]}}}},{"isAttribute":false,"isHost":false,"isSelf":false,"isSkipSelf":false,"isOptional":false,"token":{"identifier":{"reference":{"__symbol":37,"members":[]}}}},{"isAttribute":false,"isHost":false,"isSelf":false,"isSkipSelf":false,"isOptional":true,"token":{"identifier":{"reference":{"__symbol":38,"members":[]}}}},{"isAttribute":false,"isHost":false,"isSelf":false,"isSkipSelf":false,"isOptional":true,"token":{"identifier":{"reference":{"__symbol":39,"members":[]}}}}]},"deps":[{"isAttribute":false,"isHost":false,"isSelf":false,"isSkipSelf":false,"isOptional":false,"token":{"identifier":{"reference":{"__symbol":31,"members":[]}}}},{"isAttribute":false,"isHost":false,"isSelf":false,"isSkipSelf":false,"isOptional":false,"token":{"identifier":{"reference":{"__symbol":27,"members":[]}}}},{"isAttribute":false,"isHost":false,"isSelf":false,"isSkipSelf":false,"isOptional":false,"token":{"identifier":{"reference":{"__symbol":32,"members":[]}}}},{"isAttribute":false,"isHost":false,"isSelf":false,"isSkipSelf":false,"isOptional":false,"token":{"identifier":{"reference":{"__symbol":25,"members":[]}}}},{"isAttribute":false,"isHost":false,"isSelf":false,"isSkipSelf":false,"isOptional":false,"token":{"identifier":{"reference":{"__symbol":33,"members":[]}}}},{"isAttribute":false,"isHost":false,"isSelf":false,"isSkipSelf":false,"isOptional":false,"token":{"identifier":{"reference":{"__symbol":34,"members":[]}}}},{"isAttribute":false,"isHost":false,"isSelf":false,"isSkipSelf":false,"isOptional":false,"token":{"identifier":{"reference":{"__symbol":35,"members":[]}}}},{"isAttribute":false,"isHost":false,"isSelf":false,"isSkipSelf":false,"isOptional":false,"token":{"identifier":{"reference":{"__symbol":36,"members":[]}}}},{"isAttribute":false,"isHost":false,"isSelf":false,"isSkipSelf":false,"isOptional":false,"token":{"identifier":{"reference":{"__symbol":37,"members":[]}}}},{"isAttribute":false,"isHost":false,"isSelf":false,"isSkipSelf":false,"isOptional":true,"token":{"identifier":{"reference":{"__symbol":38,"members":[]}}}},{"isAttribute":false,"isHost":false,"isSelf":false,"isSkipSelf":false,"isOptional":true,"token":{"identifier":{"reference":{"__symbol":39,"members":[]}}}}],"multi":false},"module":{"reference":{"__symbol":0,"members":[]},"diDeps":[],"lifecycleHooks":[]}},{"provider":{"token":{"identifier":{"reference":{"__symbol":32,"members":[]},"diDeps":[],"lifecycleHooks":[]}},"useClass":{"reference":{"__symbol":32,"members":[]},"diDeps":[],"lifecycleHooks":[]},"useFactory":null,"deps":[],"multi":false},"module":{"reference":{"__symbol":0,"members":[]},"diDeps":[],"lifecycleHooks":[]}},{"provider":{"token":{"identifier":{"reference":{"__symbol":40,"members":[]}}},"useClass":null,"useFactory":{"reference":{"__symbol":41,"members":[]},"diDeps":[{"isAttribute":false,"isHost":false,"isSelf":false,"isSkipSelf":false,"isOptional":false,"token":{"identifier":{"reference":{"__symbol":29,"members":[]}}}}]},"deps":[{"isAttribute":false,"isHost":false,"isSelf":false,"isSkipSelf":false,"isOptional":false,"token":{"identifier":{"reference":{"__symbol":29,"members":[]}}}}],"multi":false},"module":{"reference":{"__symbol":0,"members":[]},"diDeps":[],"lifecycleHooks":[]}},{"provider":{"token":{"identifier":{"reference":{"__symbol":34,"members":[]}}},"useClass":{"reference":{"__symbol":42,"members":[]},"diDeps":[{"isAttribute":false,"isHost":false,"isSelf":false,"isSkipSelf":false,"isOptional":false,"token":{"identifier":{"reference":{"__symbol":35,"members":[]}}}},{"isAttribute":false,"isHost":false,"isSelf":false,"isSkipSelf":false,"isOptional":true,"token":{"identifier":{"reference":{"__symbol":43,"members":[]}}}}],"lifecycleHooks":[]},"useFactory":null,"deps":[{"isAttribute":false,"isHost":false,"isSelf":false,"isSkipSelf":false,"isOptional":false,"token":{"identifier":{"reference":{"__symbol":35,"members":[]}}}},{"isAttribute":false,"isHost":false,"isSelf":false,"isSkipSelf":false,"isOptional":true,"token":{"identifier":{"reference":{"__symbol":43,"members":[]}}}}],"multi":false},"module":{"reference":{"__symbol":0,"members":[]},"diDeps":[],"lifecycleHooks":[]}},{"provider":{"token":{"identifier":{"reference":{"__symbol":44,"members":[]},"diDeps":[{"isAttribute":false,"isHost":false,"isSelf":false,"isSkipSelf":false,"isOptional":false,"token":{"identifier":{"reference":{"__symbol":29,"members":[]}}}},{"isAttribute":false,"isHost":false,"isSelf":false,"isSkipSelf":false,"isOptional":false,"token":{"identifier":{"reference":{"__symbol":34,"members":[]}}}},{"isAttribute":false,"isHost":false,"isSelf":false,"isSkipSelf":false,"isOptional":false,"token":{"identifier":{"reference":{"__symbol":35,"members":[]}}}},{"isAttribute":false,"isHost":false,"isSelf":false,"isSkipSelf":false,"isOptional":false,"token":{"identifier":{"reference":{"__symbol":33,"members":[]}}}},{"isAttribute":false,"isHost":false,"isSelf":false,"isSkipSelf":false,"isOptional":false,"token":{"identifier":{"reference":{"__symbol":45,"members":[]}}}}],"lifecycleHooks":[1]}},"useClass":{"reference":{"__symbol":44,"members":[]},"diDeps":[{"isAttribute":false,"isHost":false,"isSelf":false,"isSkipSelf":false,"isOptional":false,"token":{"identifier":{"reference":{"__symbol":29,"members":[]}}}},{"isAttribute":false,"isHost":false,"isSelf":false,"isSkipSelf":false,"isOptional":false,"token":{"identifier":{"reference":{"__symbol":34,"members":[]}}}},{"isAttribute":false,"isHost":false,"isSelf":false,"isSkipSelf":false,"isOptional":false,"token":{"identifier":{"reference":{"__symbol":35,"members":[]}}}},{"isAttribute":false,"isHost":false,"isSelf":false,"isSkipSelf":false,"isOptional":false,"token":{"identifier":{"reference":{"__symbol":33,"members":[]}}}},{"isAttribute":false,"isHost":false,"isSelf":false,"isSkipSelf":false,"isOptional":false,"token":{"identifier":{"reference":{"__symbol":45,"members":[]}}}}],"lifecycleHooks":[1]},"useFactory":null,"deps":[{"isAttribute":false,"isHost":false,"isSelf":false,"isSkipSelf":false,"isOptional":false,"token":{"identifier":{"reference":{"__symbol":29,"members":[]}}}},{"isAttribute":false,"isHost":false,"isSelf":false,"isSkipSelf":false,"isOptional":false,"token":{"identifier":{"reference":{"__symbol":34,"members":[]}}}},{"isAttribute":false,"isHost":false,"isSelf":false,"isSkipSelf":false,"isOptional":false,"token":{"identifier":{"reference":{"__symbol":35,"members":[]}}}},{"isAttribute":false,"isHost":false,"isSelf":false,"isSkipSelf":false,"isOptional":false,"token":{"identifier":{"reference":{"__symbol":33,"members":[]}}}},{"isAttribute":false,"isHost":false,"isSelf":false,"isSkipSelf":false,"isOptional":false,"token":{"identifier":{"reference":{"__symbol":45,"members":[]}}}}],"multi":false},"module":{"reference":{"__symbol":0,"members":[]},"diDeps":[],"lifecycleHooks":[]}},{"provider":{"token":{"identifier":{"reference":{"__symbol":46,"members":[]},"diDeps":[],"lifecycleHooks":[]}},"useClass":{"reference":{"__symbol":46,"members":[]},"diDeps":[],"lifecycleHooks":[]},"useFactory":null,"deps":[],"multi":false},"module":{"reference":{"__symbol":0,"members":[]},"diDeps":[],"lifecycleHooks":[]}},{"provider":{"token":{"identifier":{"reference":{"__symbol":47,"members":[]},"diDeps":[],"lifecycleHooks":[]}},"useClass":{"reference":{"__symbol":47,"members":[]},"diDeps":[],"lifecycleHooks":[]},"useFactory":null,"deps":[],"multi":false},"module":{"reference":{"__symbol":0,"members":[]},"diDeps":[],"lifecycleHooks":[]}},{"provider":{"token":{"identifier":{"reference":{"__symbol":37,"members":[]}}},"useClass":null,"useValue":{"enableTracing":false},"useFactory":null,"multi":false},"module":{"reference":{"__symbol":0,"members":[]},"diDeps":[],"lifecycleHooks":[]}},{"provider":{"token":{"identifier":{"reference":{"__symbol":36,"members":[]}}},"useClass":null,"useValue":[{"path":"","component":{"__symbol":1,"members":[]}},{"path":"post/:id","component":{"__symbol":3,"members":[]}}],"useFactory":null,"multi":true},"module":{"reference":{"__symbol":0,"members":[]},"diDeps":[],"lifecycleHooks":[]}},{"provider":{"token":{"identifier":{"reference":{"__symbol":48,"members":[]}}},"useClass":null,"useFactory":{"reference":{"__symbol":49,"members":[]},"diDeps":[{"isAttribute":false,"isHost":false,"isSelf":false,"isSkipSelf":true,"isOptional":true,"token":{"identifier":{"reference":{"__symbol":29,"members":[]}}}}]},"deps":[{"isAttribute":false,"isHost":false,"isSelf":false,"isSkipSelf":true,"isOptional":true,"token":{"identifier":{"reference":{"__symbol":29,"members":[]}}}}],"multi":false},"module":{"reference":{"__symbol":0,"members":[]},"diDeps":[],"lifecycleHooks":[]}},{"provider":{"token":{"identifier":{"reference":{"__symbol":37,"members":[]}}},"useClass":null,"useValue":{},"useFactory":null,"multi":false},"module":{"reference":{"__symbol":0,"members":[]},"diDeps":[],"lifecycleHooks":[]}},{"provider":{"token":{"identifier":{"reference":{"__symbol":26,"members":[]}}},"useClass":null,"useFactory":{"reference":{"__symbol":50,"members":[]},"diDeps":[{"isAttribute":false,"isHost":false,"isSelf":false,"isSkipSelf":false,"isOptional":false,"token":{"identifier":{"reference":{"__symbol":51,"members":[]}}}},{"isAttribute":false,"isHost":false,"isSelf":false,"isSkipSelf":false,"isOptional":true,"token":{"identifier":{"reference":{"__symbol":52,"members":[]}}}},{"isAttribute":false,"isHost":false,"isSelf":false,"isSkipSelf":false,"isOptional":false,"token":{"identifier":{"reference":{"__symbol":37,"members":[]}}}}]},"deps":[{"isAttribute":false,"isHost":false,"isSelf":false,"isSkipSelf":false,"isOptional":false,"token":{"identifier":{"reference":{"__symbol":51,"members":[]}}}},{"isAttribute":false,"isHost":false,"isSelf":false,"isSkipSelf":false,"isOptional":true,"token":{"identifier":{"reference":{"__symbol":52,"members":[]}}}},{"isAttribute":false,"isHost":false,"isSelf":false,"isSkipSelf":false,"isOptional":false,"token":{"identifier":{"reference":{"__symbol":37,"members":[]}}}}],"multi":false},"module":{"reference":{"__symbol":0,"members":[]},"diDeps":[],"lifecycleHooks":[]}},{"provider":{"token":{"identifier":{"reference":{"__symbol":45,"members":[]}}},"useClass":null,"useFactory":null,"useExisting":{"identifier":{"reference":{"__symbol":46,"members":[]}}},"multi":false},"module":{"reference":{"__symbol":0,"members":[]},"diDeps":[],"lifecycleHooks":[]}},{"provider":{"token":{"identifier":{"reference":{"__symbol":53,"members":[]}}},"useClass":null,"useFactory":{"reference":{"__symbol":54,"members":[]},"diDeps":[]},"deps":[],"multi":true},"module":{"reference":{"__symbol":0,"members":[]},"diDeps":[],"lifecycleHooks":[]}},{"provider":{"token":{"identifier":{"reference":{"__symbol":55,"members":[]},"diDeps":[{"isAttribute":false,"isHost":false,"isSelf":false,"isSkipSelf":false,"isOptional":false,"token":{"identifier":{"reference":{"__symbol":33,"members":[]}}}}],"lifecycleHooks":[]}},"useClass":{"reference":{"__symbol":55,"members":[]},"diDeps":[{"isAttribute":false,"isHost":false,"isSelf":false,"isSkipSelf":false,"isOptional":false,"token":{"identifier":{"reference":{"__symbol":33,"members":[]}}}}],"lifecycleHooks":[]},"useFactory":null,"deps":[{"isAttribute":false,"isHost":false,"isSelf":false,"isSkipSelf":false,"isOptional":false,"token":{"identifier":{"reference":{"__symbol":33,"members":[]}}}}],"multi":false},"module":{"reference":{"__symbol":0,"members":[]},"diDeps":[],"lifecycleHooks":[]}},{"provider":{"token":{"identifier":{"reference":{"__symbol":56,"members":[]}}},"useClass":null,"useFactory":{"reference":{"__symbol":57,"members":[]},"diDeps":[{"isAttribute":false,"isHost":false,"isSelf":false,"isSkipSelf":false,"isOptional":false,"token":{"identifier":{"reference":{"__symbol":55,"members":[]}}}}]},"deps":[{"isAttribute":false,"isHost":false,"isSelf":false,"isSkipSelf":false,"isOptional":false,"token":{"identifier":{"reference":{"__symbol":55,"members":[]}}}}],"multi":true},"module":{"reference":{"__symbol":0,"members":[]},"diDeps":[],"lifecycleHooks":[]}},{"provider":{"token":{"identifier":{"reference":{"__symbol":58,"members":[]}}},"useClass":null,"useFactory":{"reference":{"__symbol":59,"members":[]},"diDeps":[{"isAttribute":false,"isHost":false,"isSelf":false,"isSkipSelf":false,"isOptional":false,"token":{"identifier":{"reference":{"__symbol":55,"members":[]}}}}]},"deps":[{"isAttribute":false,"isHost":false,"isSelf":false,"isSkipSelf":false,"isOptional":false,"token":{"identifier":{"reference":{"__symbol":55,"members":[]}}}}],"multi":false},"module":{"reference":{"__symbol":0,"members":[]},"diDeps":[],"lifecycleHooks":[]}},{"provider":{"token":{"identifier":{"reference":{"__symbol":60,"members":[]}}},"useClass":null,"useFactory":null,"useExisting":{"identifier":{"reference":{"__symbol":58,"members":[]}}},"multi":true},"module":{"reference":{"__symbol":0,"members":[]},"diDeps":[],"lifecycleHooks":[]}},{"provider":{"token":{"identifier":{"reference":{"__symbol":61,"members":[]},"diDeps":[{"isAttribute":false,"isHost":false,"isSelf":false,"isSkipSelf":false,"isOptional":false,"token":{"identifier":{"reference":{"__symbol":18,"members":[]}}}}],"lifecycleHooks":[]}},"useClass":{"reference":{"__symbol":61,"members":[]},"diDeps":[{"isAttribute":false,"isHost":false,"isSelf":false,"isSkipSelf":false,"isOptional":false,"token":{"identifier":{"reference":{"__symbol":18,"members":[]}}}}],"lifecycleHooks":[]},"useFactory":null,"deps":[{"isAttribute":false,"isHost":false,"isSelf":false,"isSkipSelf":false,"isOptional":false,"token":{"identifier":{"reference":{"__symbol":18,"members":[]}}}}],"multi":false},"module":{"reference":{"__symbol":0,"members":[]},"diDeps":[],"lifecycleHooks":[]}},{"provider":{"token":{"identifier":{"reference":{"__symbol":62,"members":[]},"diDeps":[{"isAttribute":false,"isHost":false,"isSelf":false,"isSkipSelf":false,"isOptional":false,"token":{"identifier":{"reference":{"__symbol":18,"members":[]}}}}],"lifecycleHooks":[]}},"useClass":{"reference":{"__symbol":62,"members":[]},"diDeps":[{"isAttribute":false,"isHost":false,"isSelf":false,"isSkipSelf":false,"isOptional":false,"token":{"identifier":{"reference":{"__symbol":18,"members":[]}}}}],"lifecycleHooks":[]},"useFactory":null,"deps":[{"isAttribute":false,"isHost":false,"isSelf":false,"isSkipSelf":false,"isOptional":false,"token":{"identifier":{"reference":{"__symbol":18,"members":[]}}}}],"multi":false},"module":{"reference":{"__symbol":0,"members":[]},"diDeps":[],"lifecycleHooks":[]}}],"modules":[{"reference":{"__symbol":11,"members":[]},"diDeps":[],"lifecycleHooks":[]},{"reference":{"__symbol":20,"members":[]},"diDeps":[],"lifecycleHooks":[]},{"reference":{"__symbol":24,"members":[]},"diDeps":[],"lifecycleHooks":[]},{"reference":{"__symbol":63,"members":[]},"diDeps":[{"isAttribute":false,"isHost":false,"isSelf":false,"isSkipSelf":false,"isOptional":true,"token":{"identifier":{"reference":{"__symbol":48,"members":[]}}}},{"isAttribute":false,"isHost":false,"isSelf":false,"isSkipSelf":false,"isOptional":true,"token":{"identifier":{"reference":{"__symbol":29,"members":[]}}}}],"lifecycleHooks":[]},{"reference":{"__symbol":0,"members":[]},"diDeps":[],"lifecycleHooks":[]}],"exportedDirectives":[],"exportedPipes":[]}}],"symbols":[{"__symbol":0,"name":"AppModule","filePath":"/Users/elysekolker/dev/personal/chapter-12-frameworks/angular2/src/app/app.module.d.ts"},{"__symbol":1,"name":"PostListComponent","filePath":"/Users/elysekolker/dev/personal/chapter-12-frameworks/angular2/src/app/post-list/post-list.component.d.ts"},{"__symbol":2,"name":"PostListComponentNgFactory","filePath":"/Users/elysekolker/dev/personal/chapter-12-frameworks/angular2/src/app/post-list/post-list.component.ngfactory.d.ts"},{"__symbol":3,"name":"PostDetailComponent","filePath":"/Users/elysekolker/dev/personal/chapter-12-frameworks/angular2/src/app/post-detail/post-detail.component.d.ts"},{"__symbol":4,"name":"PostDetailComponentNgFactory","filePath":"/Users/elysekolker/dev/personal/chapter-12-frameworks/angular2/src/app/post-detail/post-detail.component.ngfactory.d.ts"},{"__symbol":5,"name":"AppComponent","filePath":"/Users/elysekolker/dev/personal/chapter-12-frameworks/angular2/src/app/app.component.d.ts"},{"__symbol":6,"name":"AppComponentNgFactory","filePath":"/Users/elysekolker/dev/personal/chapter-12-frameworks/angular2/src/app/app.component.ngfactory.d.ts"},{"__symbol":7,"name":"Http","filePath":"/Users/elysekolker/dev/personal/chapter-12-frameworks/angular2/node_modules/@angular/http/http.d.ts"},{"__symbol":8,"name":"ɵc","filePath":"/Users/elysekolker/dev/personal/chapter-12-frameworks/angular2/node_modules/@angular/http/http.d.ts"},{"__symbol":9,"name":"XHRBackend","filePath":"/Users/elysekolker/dev/personal/chapter-12-frameworks/angular2/node_modules/@angular/http/http.d.ts"},{"__symbol":10,"name":"RequestOptions","filePath":"/Users/elysekolker/dev/personal/chapter-12-frameworks/angular2/node_modules/@angular/http/http.d.ts"},{"__symbol":11,"name":"HttpModule","filePath":"/Users/elysekolker/dev/personal/chapter-12-frameworks/angular2/node_modules/@angular/http/http.d.ts"},{"__symbol":12,"name":"BrowserXhr","filePath":"/Users/elysekolker/dev/personal/chapter-12-frameworks/angular2/node_modules/@angular/http/http.d.ts"},{"__symbol":13,"name":"BaseRequestOptions","filePath":"/Users/elysekolker/dev/personal/chapter-12-frameworks/angular2/node_modules/@angular/http/http.d.ts"},{"__symbol":14,"name":"ResponseOptions","filePath":"/Users/elysekolker/dev/personal/chapter-12-frameworks/angular2/node_modules/@angular/http/http.d.ts"},{"__symbol":15,"name":"BaseResponseOptions","filePath":"/Users/elysekolker/dev/personal/chapter-12-frameworks/angular2/node_modules/@angular/http/http.d.ts"},{"__symbol":16,"name":"XSRFStrategy","filePath":"/Users/elysekolker/dev/personal/chapter-12-frameworks/angular2/node_modules/@angular/http/http.d.ts"},{"__symbol":17,"name":"ɵb","filePath":"/Users/elysekolker/dev/personal/chapter-12-frameworks/angular2/node_modules/@angular/http/http.d.ts"},{"__symbol":18,"name":"TransferHttp","filePath":"/Users/elysekolker/dev/personal/chapter-12-frameworks/angular2/src/modules/transfer-http/transfer-http.d.ts"},{"__symbol":19,"name":"TransferState","filePath":"/Users/elysekolker/dev/personal/chapter-12-frameworks/angular2/src/modules/transfer-state/transfer-state.d.ts"},{"__symbol":20,"name":"TransferHttpModule","filePath":"/Users/elysekolker/dev/personal/chapter-12-frameworks/angular2/src/modules/transfer-http/transfer-http.module.d.ts"},{"__symbol":21,"name":"NgLocalization","filePath":"/Users/elysekolker/dev/personal/chapter-12-frameworks/angular2/node_modules/@angular/common/common.d.ts"},{"__symbol":22,"name":"NgLocaleLocalization","filePath":"/Users/elysekolker/dev/personal/chapter-12-frameworks/angular2/node_modules/@angular/common/common.d.ts"},{"__symbol":23,"name":"LOCALE_ID","filePath":"/Users/elysekolker/dev/personal/chapter-12-frameworks/angular2/node_modules/@angular/core/core.d.ts"},{"__symbol":24,"name":"CommonModule","filePath":"/Users/elysekolker/dev/personal/chapter-12-frameworks/angular2/node_modules/@angular/common/common.d.ts"},{"__symbol":25,"name":"Location","filePath":"/Users/elysekolker/dev/personal/chapter-12-frameworks/angular2/node_modules/@angular/common/common.d.ts"},{"__symbol":26,"name":"LocationStrategy","filePath":"/Users/elysekolker/dev/personal/chapter-12-frameworks/angular2/node_modules/@angular/common/common.d.ts"},{"__symbol":27,"name":"UrlSerializer","filePath":"/Users/elysekolker/dev/personal/chapter-12-frameworks/angular2/node_modules/@angular/router/router.d.ts"},{"__symbol":28,"name":"DefaultUrlSerializer","filePath":"/Users/elysekolker/dev/personal/chapter-12-frameworks/angular2/node_modules/@angular/router/router.d.ts"},{"__symbol":29,"name":"Router","filePath":"/Users/elysekolker/dev/personal/chapter-12-frameworks/angular2/node_modules/@angular/router/router.d.ts"},{"__symbol":30,"name":"ɵe","filePath":"/Users/elysekolker/dev/personal/chapter-12-frameworks/angular2/node_modules/@angular/router/router.d.ts"},{"__symbol":31,"name":"ApplicationRef","filePath":"/Users/elysekolker/dev/personal/chapter-12-frameworks/angular2/node_modules/@angular/core/core.d.ts"},{"__symbol":32,"name":"ChildrenOutletContexts","filePath":"/Users/elysekolker/dev/personal/chapter-12-frameworks/angular2/node_modules/@angular/router/router.d.ts"},{"__symbol":33,"name":"Injector","filePath":"/Users/elysekolker/dev/personal/chapter-12-frameworks/angular2/node_modules/@angular/core/core.d.ts"},{"__symbol":34,"name":"NgModuleFactoryLoader","filePath":"/Users/elysekolker/dev/personal/chapter-12-frameworks/angular2/node_modules/@angular/core/core.d.ts"},{"__symbol":35,"name":"Compiler","filePath":"/Users/elysekolker/dev/personal/chapter-12-frameworks/angular2/node_modules/@angular/core/core.d.ts"},{"__symbol":36,"name":"ROUTES","filePath":"/Users/elysekolker/dev/personal/chapter-12-frameworks/angular2/node_modules/@angular/router/router.d.ts"},{"__symbol":37,"name":"ROUTER_CONFIGURATION","filePath":"/Users/elysekolker/dev/personal/chapter-12-frameworks/angular2/node_modules/@angular/router/router.d.ts"},{"__symbol":38,"name":"UrlHandlingStrategy","filePath":"/Users/elysekolker/dev/personal/chapter-12-frameworks/angular2/node_modules/@angular/router/router.d.ts"},{"__symbol":39,"name":"RouteReuseStrategy","filePath":"/Users/elysekolker/dev/personal/chapter-12-frameworks/angular2/node_modules/@angular/router/router.d.ts"},{"__symbol":40,"name":"ActivatedRoute","filePath":"/Users/elysekolker/dev/personal/chapter-12-frameworks/angular2/node_modules/@angular/router/router.d.ts"},{"__symbol":41,"name":"ɵf","filePath":"/Users/elysekolker/dev/personal/chapter-12-frameworks/angular2/node_modules/@angular/router/router.d.ts"},{"__symbol":42,"name":"SystemJsNgModuleLoader","filePath":"/Users/elysekolker/dev/personal/chapter-12-frameworks/angular2/node_modules/@angular/core/core.d.ts"},{"__symbol":43,"name":"SystemJsNgModuleLoaderConfig","filePath":"/Users/elysekolker/dev/personal/chapter-12-frameworks/angular2/node_modules/@angular/core/core.d.ts"},{"__symbol":44,"name":"RouterPreloader","filePath":"/Users/elysekolker/dev/personal/chapter-12-frameworks/angular2/node_modules/@angular/router/router.d.ts"},{"__symbol":45,"name":"PreloadingStrategy","filePath":"/Users/elysekolker/dev/personal/chapter-12-frameworks/angular2/node_modules/@angular/router/router.d.ts"},{"__symbol":46,"name":"NoPreloading","filePath":"/Users/elysekolker/dev/personal/chapter-12-frameworks/angular2/node_modules/@angular/router/router.d.ts"},{"__symbol":47,"name":"PreloadAllModules","filePath":"/Users/elysekolker/dev/personal/chapter-12-frameworks/angular2/node_modules/@angular/router/router.d.ts"},{"__symbol":48,"name":"ɵa","filePath":"/Users/elysekolker/dev/personal/chapter-12-frameworks/angular2/node_modules/@angular/router/router.d.ts"},{"__symbol":49,"name":"ɵd","filePath":"/Users/elysekolker/dev/personal/chapter-12-frameworks/angular2/node_modules/@angular/router/router.d.ts"},{"__symbol":50,"name":"ɵc","filePath":"/Users/elysekolker/dev/personal/chapter-12-frameworks/angular2/node_modules/@angular/router/router.d.ts"},{"__symbol":51,"name":"PlatformLocation","filePath":"/Users/elysekolker/dev/personal/chapter-12-frameworks/angular2/node_modules/@angular/common/common.d.ts"},{"__symbol":52,"name":"APP_BASE_HREF","filePath":"/Users/elysekolker/dev/personal/chapter-12-frameworks/angular2/node_modules/@angular/common/common.d.ts"},{"__symbol":53,"name":"NgProbeToken","filePath":"/Users/elysekolker/dev/personal/chapter-12-frameworks/angular2/node_modules/@angular/core/core.d.ts"},{"__symbol":54,"name":"ɵb","filePath":"/Users/elysekolker/dev/personal/chapter-12-frameworks/angular2/node_modules/@angular/router/router.d.ts"},{"__symbol":55,"name":"ɵg","filePath":"/Users/elysekolker/dev/personal/chapter-12-frameworks/angular2/node_modules/@angular/router/router.d.ts"},{"__symbol":56,"name":"APP_INITIALIZER","filePath":"/Users/elysekolker/dev/personal/chapter-12-frameworks/angular2/node_modules/@angular/core/core.d.ts"},{"__symbol":57,"name":"ɵh","filePath":"/Users/elysekolker/dev/personal/chapter-12-frameworks/angular2/node_modules/@angular/router/router.d.ts"},{"__symbol":58,"name":"ROUTER_INITIALIZER","filePath":"/Users/elysekolker/dev/personal/chapter-12-frameworks/angular2/node_modules/@angular/router/router.d.ts"},{"__symbol":59,"name":"ɵi","filePath":"/Users/elysekolker/dev/personal/chapter-12-frameworks/angular2/node_modules/@angular/router/router.d.ts"},{"__symbol":60,"name":"APP_BOOTSTRAP_LISTENER","filePath":"/Users/elysekolker/dev/personal/chapter-12-frameworks/angular2/node_modules/@angular/core/core.d.ts"},{"__symbol":61,"name":"CommentsService","filePath":"/Users/elysekolker/dev/personal/chapter-12-frameworks/angular2/src/app/services/comments.service.d.ts"},{"__symbol":62,"name":"PostsService","filePath":"/Users/elysekolker/dev/personal/chapter-12-frameworks/angular2/src/app/services/posts.service.d.ts"},{"__symbol":63,"name":"RouterModule","filePath":"/Users/elysekolker/dev/personal/chapter-12-frameworks/angular2/node_modules/@angular/router/router.d.ts"}]}