{"summaries":[{"symbol":{"__symbol":0,"members":[]},"metadata":{"__symbolic":"function","parameters":["appRef","transferState"],"value":{"__symbolic":"error","message":"Function call not supported","line":13,"character":9}}},{"symbol":{"__symbol":1,"members":[]},"metadata":{"__symbolic":"class"},"type":{"summaryKind":2,"type":{"reference":{"__symbol":1,"members":[]},"diDeps":[],"lifecycleHooks":[]},"entryComponents":[{"componentType":{"__symbol":2,"members":[]},"componentFactory":{"__symbol":3,"members":[]}}],"providers":[{"provider":{"token":{"identifier":{"reference":{"__symbol":4,"members":[]}}},"useClass":null,"useFactory":{"reference":{"__symbol":5,"members":[]},"diDeps":[{"isAttribute":false,"isHost":false,"isSelf":false,"isSkipSelf":false,"isOptional":false,"token":{"identifier":{"reference":{"__symbol":6,"members":[]}}}},{"isAttribute":false,"isHost":false,"isSelf":false,"isSkipSelf":false,"isOptional":false,"token":{"identifier":{"reference":{"__symbol":7,"members":[]}}}}]},"deps":[{"isAttribute":false,"isHost":false,"isSelf":false,"isSkipSelf":false,"isOptional":false,"token":{"identifier":{"reference":{"__symbol":6,"members":[]}}}},{"isAttribute":false,"isHost":false,"isSelf":false,"isSkipSelf":false,"isOptional":false,"token":{"identifier":{"reference":{"__symbol":7,"members":[]}}}}],"multi":false},"module":{"reference":{"__symbol":8,"members":[]},"diDeps":[],"lifecycleHooks":[]}},{"provider":{"token":{"identifier":{"reference":{"__symbol":9,"members":[]},"diDeps":[],"lifecycleHooks":[]}},"useClass":{"reference":{"__symbol":9,"members":[]},"diDeps":[],"lifecycleHooks":[]},"useFactory":null,"deps":[],"multi":false},"module":{"reference":{"__symbol":8,"members":[]},"diDeps":[],"lifecycleHooks":[]}},{"provider":{"token":{"identifier":{"reference":{"__symbol":7,"members":[]}}},"useClass":{"reference":{"__symbol":10,"members":[]},"diDeps":[],"lifecycleHooks":[]},"useFactory":null,"deps":[],"multi":false},"module":{"reference":{"__symbol":8,"members":[]},"diDeps":[],"lifecycleHooks":[]}},{"provider":{"token":{"identifier":{"reference":{"__symbol":11,"members":[]}}},"useClass":{"reference":{"__symbol":12,"members":[]},"diDeps":[],"lifecycleHooks":[]},"useFactory":null,"deps":[],"multi":false},"module":{"reference":{"__symbol":8,"members":[]},"diDeps":[],"lifecycleHooks":[]}},{"provider":{"token":{"identifier":{"reference":{"__symbol":6,"members":[]},"diDeps":[{"isAttribute":false,"isHost":false,"isSelf":false,"isSkipSelf":false,"isOptional":false,"token":{"identifier":{"reference":{"__symbol":9,"members":[]}}}},{"isAttribute":false,"isHost":false,"isSelf":false,"isSkipSelf":false,"isOptional":false,"token":{"identifier":{"reference":{"__symbol":11,"members":[]}}}},{"isAttribute":false,"isHost":false,"isSelf":false,"isSkipSelf":false,"isOptional":false,"token":{"identifier":{"reference":{"__symbol":13,"members":[]}}}}],"lifecycleHooks":[]}},"useClass":{"reference":{"__symbol":6,"members":[]},"diDeps":[{"isAttribute":false,"isHost":false,"isSelf":false,"isSkipSelf":false,"isOptional":false,"token":{"identifier":{"reference":{"__symbol":9,"members":[]}}}},{"isAttribute":false,"isHost":false,"isSelf":false,"isSkipSelf":false,"isOptional":false,"token":{"identifier":{"reference":{"__symbol":11,"members":[]}}}},{"isAttribute":false,"isHost":false,"isSelf":false,"isSkipSelf":false,"isOptional":false,"token":{"identifier":{"reference":{"__symbol":13,"members":[]}}}}],"lifecycleHooks":[]},"useFactory":null,"deps":[{"isAttribute":false,"isHost":false,"isSelf":false,"isSkipSelf":false,"isOptional":false,"token":{"identifier":{"reference":{"__symbol":9,"members":[]}}}},{"isAttribute":false,"isHost":false,"isSelf":false,"isSkipSelf":false,"isOptional":false,"token":{"identifier":{"reference":{"__symbol":11,"members":[]}}}},{"isAttribute":false,"isHost":false,"isSelf":false,"isSkipSelf":false,"isOptional":false,"token":{"identifier":{"reference":{"__symbol":13,"members":[]}}}}],"multi":false},"module":{"reference":{"__symbol":8,"members":[]},"diDeps":[],"lifecycleHooks":[]}},{"provider":{"token":{"identifier":{"reference":{"__symbol":13,"members":[]}}},"useClass":null,"useFactory":{"reference":{"__symbol":14,"members":[]},"diDeps":[]},"deps":[],"multi":false},"module":{"reference":{"__symbol":8,"members":[]},"diDeps":[],"lifecycleHooks":[]}},{"provider":{"token":{"identifier":{"reference":{"__symbol":15,"members":[]}}},"useClass":{"reference":{"__symbol":16,"members":[]},"diDeps":[{"isAttribute":false,"isHost":false,"isSelf":false,"isSkipSelf":false,"isOptional":false,"token":{"identifier":{"reference":{"__symbol":17,"members":[]}}}}],"lifecycleHooks":[]},"useFactory":null,"deps":[{"isAttribute":false,"isHost":false,"isSelf":false,"isSkipSelf":false,"isOptional":false,"token":{"identifier":{"reference":{"__symbol":17,"members":[]}}}}],"multi":false},"module":{"reference":{"__symbol":18,"members":[]},"diDeps":[],"lifecycleHooks":[]}},{"provider":{"token":{"identifier":{"reference":{"__symbol":19,"members":[]},"diDeps":[{"isAttribute":false,"isHost":false,"isSelf":false,"isSkipSelf":false,"isOptional":false,"token":{"identifier":{"reference":{"__symbol":20,"members":[]}}}},{"isAttribute":false,"isHost":false,"isSelf":false,"isSkipSelf":false,"isOptional":false,"token":{"identifier":{"reference":{"__symbol":21,"members":[]}}}},{"isAttribute":false,"isHost":false,"isSelf":false,"isSkipSelf":false,"isOptional":false,"token":{"identifier":{"reference":{"__symbol":22,"members":[]}}}},{"isAttribute":false,"isHost":false,"isSelf":false,"isSkipSelf":false,"isOptional":false,"token":{"identifier":{"reference":{"__symbol":23,"members":[]}}}},{"isAttribute":false,"isHost":false,"isSelf":false,"isSkipSelf":false,"isOptional":false,"token":{"identifier":{"reference":{"__symbol":24,"members":[]}}}},{"isAttribute":false,"isHost":false,"isSelf":false,"isSkipSelf":false,"isOptional":false,"token":{"identifier":{"reference":{"__symbol":25,"members":[]}}}}],"lifecycleHooks":[1]}},"useClass":{"reference":{"__symbol":19,"members":[]},"diDeps":[{"isAttribute":false,"isHost":false,"isSelf":false,"isSkipSelf":false,"isOptional":false,"token":{"identifier":{"reference":{"__symbol":20,"members":[]}}}},{"isAttribute":false,"isHost":false,"isSelf":false,"isSkipSelf":false,"isOptional":false,"token":{"identifier":{"reference":{"__symbol":21,"members":[]}}}},{"isAttribute":false,"isHost":false,"isSelf":false,"isSkipSelf":false,"isOptional":false,"token":{"identifier":{"reference":{"__symbol":22,"members":[]}}}},{"isAttribute":false,"isHost":false,"isSelf":false,"isSkipSelf":false,"isOptional":false,"token":{"identifier":{"reference":{"__symbol":23,"members":[]}}}},{"isAttribute":false,"isHost":false,"isSelf":false,"isSkipSelf":false,"isOptional":false,"token":{"identifier":{"reference":{"__symbol":24,"members":[]}}}},{"isAttribute":false,"isHost":false,"isSelf":false,"isSkipSelf":false,"isOptional":false,"token":{"identifier":{"reference":{"__symbol":25,"members":[]}}}}],"lifecycleHooks":[1]},"useFactory":null,"deps":[{"isAttribute":false,"isHost":false,"isSelf":false,"isSkipSelf":false,"isOptional":false,"token":{"identifier":{"reference":{"__symbol":20,"members":[]}}}},{"isAttribute":false,"isHost":false,"isSelf":false,"isSkipSelf":false,"isOptional":false,"token":{"identifier":{"reference":{"__symbol":21,"members":[]}}}},{"isAttribute":false,"isHost":false,"isSelf":false,"isSkipSelf":false,"isOptional":false,"token":{"identifier":{"reference":{"__symbol":22,"members":[]}}}},{"isAttribute":false,"isHost":false,"isSelf":false,"isSkipSelf":false,"isOptional":false,"token":{"identifier":{"reference":{"__symbol":23,"members":[]}}}},{"isAttribute":false,"isHost":false,"isSelf":false,"isSkipSelf":false,"isOptional":false,"token":{"identifier":{"reference":{"__symbol":24,"members":[]}}}},{"isAttribute":false,"isHost":false,"isSelf":false,"isSkipSelf":false,"isOptional":false,"token":{"identifier":{"reference":{"__symbol":25,"members":[]}}}}],"multi":false},"module":{"reference":{"__symbol":26,"members":[]},"diDeps":[{"isAttribute":false,"isHost":false,"isSelf":false,"isSkipSelf":false,"isOptional":false,"token":{"identifier":{"reference":{"__symbol":27,"members":[]}}}}],"lifecycleHooks":[]}},{"provider":{"token":{"identifier":{"reference":{"__symbol":27,"members":[]}}},"useClass":null,"useFactory":null,"useExisting":{"identifier":{"reference":{"__symbol":19,"members":[]}}},"multi":false},"module":{"reference":{"__symbol":26,"members":[]},"diDeps":[{"isAttribute":false,"isHost":false,"isSelf":false,"isSkipSelf":false,"isOptional":false,"token":{"identifier":{"reference":{"__symbol":27,"members":[]}}}}],"lifecycleHooks":[]}},{"provider":{"token":{"identifier":{"reference":{"__symbol":25,"members":[]},"diDeps":[{"isAttribute":false,"isHost":false,"isSelf":false,"isSkipSelf":false,"isOptional":true,"token":{"identifier":{"reference":{"__symbol":28,"members":[]}}}}],"lifecycleHooks":[]}},"useClass":{"reference":{"__symbol":25,"members":[]},"diDeps":[{"isAttribute":false,"isHost":false,"isSelf":false,"isSkipSelf":false,"isOptional":true,"token":{"identifier":{"reference":{"__symbol":28,"members":[]}}}}],"lifecycleHooks":[]},"useFactory":null,"deps":[{"isAttribute":false,"isHost":false,"isSelf":false,"isSkipSelf":false,"isOptional":true,"token":{"identifier":{"reference":{"__symbol":28,"members":[]}}}}],"multi":false},"module":{"reference":{"__symbol":26,"members":[]},"diDeps":[{"isAttribute":false,"isHost":false,"isSelf":false,"isSkipSelf":false,"isOptional":false,"token":{"identifier":{"reference":{"__symbol":27,"members":[]}}}}],"lifecycleHooks":[]}},{"provider":{"token":{"identifier":{"reference":{"__symbol":29,"members":[]},"diDeps":[],"lifecycleHooks":[]}},"useClass":{"reference":{"__symbol":29,"members":[]},"diDeps":[],"lifecycleHooks":[]},"useFactory":null,"deps":[],"multi":false},"module":{"reference":{"__symbol":26,"members":[]},"diDeps":[{"isAttribute":false,"isHost":false,"isSelf":false,"isSkipSelf":false,"isOptional":false,"token":{"identifier":{"reference":{"__symbol":27,"members":[]}}}}],"lifecycleHooks":[]}},{"provider":{"token":{"identifier":{"reference":{"__symbol":30,"members":[]}}},"useClass":null,"useFactory":{"reference":{"__symbol":31,"members":[]},"diDeps":[]},"deps":[],"multi":false},"module":{"reference":{"__symbol":26,"members":[]},"diDeps":[{"isAttribute":false,"isHost":false,"isSelf":false,"isSkipSelf":false,"isOptional":false,"token":{"identifier":{"reference":{"__symbol":27,"members":[]}}}}],"lifecycleHooks":[]}},{"provider":{"token":{"identifier":{"reference":{"__symbol":32,"members":[]}}},"useClass":null,"useFactory":{"reference":{"__symbol":33,"members":[]},"diDeps":[]},"deps":[],"multi":false},"module":{"reference":{"__symbol":26,"members":[]},"diDeps":[{"isAttribute":false,"isHost":false,"isSelf":false,"isSkipSelf":false,"isOptional":false,"token":{"identifier":{"reference":{"__symbol":27,"members":[]}}}}],"lifecycleHooks":[]}},{"provider":{"token":{"identifier":{"reference":{"__symbol":34,"members":[]}}},"useClass":null,"useFactory":{"reference":{"__symbol":35,"members":[]},"diDeps":[]},"deps":[],"multi":false},"module":{"reference":{"__symbol":26,"members":[]},"diDeps":[{"isAttribute":false,"isHost":false,"isSelf":false,"isSkipSelf":false,"isOptional":false,"token":{"identifier":{"reference":{"__symbol":27,"members":[]}}}}],"lifecycleHooks":[]}},{"provider":{"token":{"identifier":{"reference":{"__symbol":17,"members":[]}}},"useClass":null,"useFactory":{"reference":{"__symbol":36,"members":[]},"diDeps":[{"isAttribute":false,"isHost":false,"isSelf":false,"isSkipSelf":true,"isOptional":true,"token":{"identifier":{"reference":{"__symbol":17,"members":[]}}}}]},"deps":[{"isAttribute":false,"isHost":false,"isSelf":false,"isSkipSelf":true,"isOptional":true,"token":{"identifier":{"reference":{"__symbol":17,"members":[]}}}}],"multi":false},"module":{"reference":{"__symbol":26,"members":[]},"diDeps":[{"isAttribute":false,"isHost":false,"isSelf":false,"isSkipSelf":false,"isOptional":false,"token":{"identifier":{"reference":{"__symbol":27,"members":[]}}}}],"lifecycleHooks":[]}},{"provider":{"token":{"identifier":{"reference":{"__symbol":37,"members":[]}}},"useClass":null,"useFactory":null,"useExisting":{"identifier":{"reference":{"__symbol":38,"members":[]}}},"multi":false},"module":{"reference":{"__symbol":39,"members":[]},"diDeps":[{"isAttribute":false,"isHost":false,"isSelf":false,"isSkipSelf":true,"isOptional":true,"token":{"identifier":{"reference":{"__symbol":39,"members":[]}}}}],"lifecycleHooks":[]}},{"provider":{"token":{"identifier":{"reference":{"__symbol":38,"members":[]}}},"useClass":{"reference":{"__symbol":40,"members":[]},"diDeps":[{"isAttribute":false,"isHost":false,"isSelf":false,"isSkipSelf":false,"isOptional":false,"token":{"identifier":{"reference":{"__symbol":41,"members":[]}}}}],"lifecycleHooks":[]},"useFactory":null,"deps":[{"isAttribute":false,"isHost":false,"isSelf":false,"isSkipSelf":false,"isOptional":false,"token":{"identifier":{"reference":{"__symbol":41,"members":[]}}}}],"multi":false},"module":{"reference":{"__symbol":39,"members":[]},"diDeps":[{"isAttribute":false,"isHost":false,"isSelf":false,"isSkipSelf":true,"isOptional":true,"token":{"identifier":{"reference":{"__symbol":39,"members":[]}}}}],"lifecycleHooks":[]}},{"provider":{"token":{"identifier":{"reference":{"__symbol":23,"members":[]}}},"useClass":null,"useFactory":{"reference":{"__symbol":42,"members":[]},"diDeps":[]},"deps":[],"multi":false},"module":{"reference":{"__symbol":39,"members":[]},"diDeps":[{"isAttribute":false,"isHost":false,"isSelf":false,"isSkipSelf":true,"isOptional":true,"token":{"identifier":{"reference":{"__symbol":39,"members":[]}}}}],"lifecycleHooks":[]}},{"provider":{"token":{"identifier":{"reference":{"__symbol":43,"members":[]}}},"useClass":{"reference":{"__symbol":44,"members":[]},"diDeps":[{"isAttribute":false,"isHost":false,"isSelf":false,"isSkipSelf":false,"isOptional":false,"token":{"identifier":{"reference":{"__symbol":41,"members":[]}}}}],"lifecycleHooks":[]},"useFactory":null,"deps":[{"isAttribute":false,"isHost":false,"isSelf":false,"isSkipSelf":false,"isOptional":false,"token":{"identifier":{"reference":{"__symbol":41,"members":[]}}}}],"multi":true},"module":{"reference":{"__symbol":39,"members":[]},"diDeps":[{"isAttribute":false,"isHost":false,"isSelf":false,"isSkipSelf":true,"isOptional":true,"token":{"identifier":{"reference":{"__symbol":39,"members":[]}}}}],"lifecycleHooks":[]}},{"provider":{"token":{"identifier":{"reference":{"__symbol":43,"members":[]}}},"useClass":{"reference":{"__symbol":45,"members":[]},"diDeps":[{"isAttribute":false,"isHost":false,"isSelf":false,"isSkipSelf":false,"isOptional":false,"token":{"identifier":{"reference":{"__symbol":41,"members":[]}}}}],"lifecycleHooks":[]},"useFactory":null,"deps":[{"isAttribute":false,"isHost":false,"isSelf":false,"isSkipSelf":false,"isOptional":false,"token":{"identifier":{"reference":{"__symbol":41,"members":[]}}}}],"multi":true},"module":{"reference":{"__symbol":39,"members":[]},"diDeps":[{"isAttribute":false,"isHost":false,"isSelf":false,"isSkipSelf":true,"isOptional":true,"token":{"identifier":{"reference":{"__symbol":39,"members":[]}}}}],"lifecycleHooks":[]}},{"provider":{"token":{"identifier":{"reference":{"__symbol":43,"members":[]}}},"useClass":{"reference":{"__symbol":46,"members":[]},"diDeps":[{"isAttribute":false,"isHost":false,"isSelf":false,"isSkipSelf":false,"isOptional":false,"token":{"identifier":{"reference":{"__symbol":41,"members":[]}}}},{"isAttribute":false,"isHost":false,"isSelf":false,"isSkipSelf":false,"isOptional":false,"token":{"identifier":{"reference":{"__symbol":47,"members":[]}}}}],"lifecycleHooks":[]},"useFactory":null,"deps":[{"isAttribute":false,"isHost":false,"isSelf":false,"isSkipSelf":false,"isOptional":false,"token":{"identifier":{"reference":{"__symbol":41,"members":[]}}}},{"isAttribute":false,"isHost":false,"isSelf":false,"isSkipSelf":false,"isOptional":false,"token":{"identifier":{"reference":{"__symbol":47,"members":[]}}}}],"multi":true},"module":{"reference":{"__symbol":39,"members":[]},"diDeps":[{"isAttribute":false,"isHost":false,"isSelf":false,"isSkipSelf":true,"isOptional":true,"token":{"identifier":{"reference":{"__symbol":39,"members":[]}}}}],"lifecycleHooks":[]}},{"provider":{"token":{"identifier":{"reference":{"__symbol":47,"members":[]}}},"useClass":{"reference":{"__symbol":48,"members":[]},"diDeps":[],"lifecycleHooks":[]},"useFactory":null,"deps":[],"multi":false},"module":{"reference":{"__symbol":39,"members":[]},"diDeps":[{"isAttribute":false,"isHost":false,"isSelf":false,"isSkipSelf":true,"isOptional":true,"token":{"identifier":{"reference":{"__symbol":39,"members":[]}}}}],"lifecycleHooks":[]}},{"provider":{"token":{"identifier":{"reference":{"__symbol":49,"members":[]},"diDeps":[{"isAttribute":false,"isHost":false,"isSelf":false,"isSkipSelf":false,"isOptional":false,"token":{"identifier":{"reference":{"__symbol":50,"members":[]}}}},{"isAttribute":false,"isHost":false,"isSelf":false,"isSkipSelf":false,"isOptional":false,"token":{"identifier":{"reference":{"__symbol":51,"members":[]}}}}],"lifecycleHooks":[]}},"useClass":{"reference":{"__symbol":49,"members":[]},"diDeps":[{"isAttribute":false,"isHost":false,"isSelf":false,"isSkipSelf":false,"isOptional":false,"token":{"identifier":{"reference":{"__symbol":50,"members":[]}}}},{"isAttribute":false,"isHost":false,"isSelf":false,"isSkipSelf":false,"isOptional":false,"token":{"identifier":{"reference":{"__symbol":51,"members":[]}}}}],"lifecycleHooks":[]},"useFactory":null,"deps":[{"isAttribute":false,"isHost":false,"isSelf":false,"isSkipSelf":false,"isOptional":false,"token":{"identifier":{"reference":{"__symbol":50,"members":[]}}}},{"isAttribute":false,"isHost":false,"isSelf":false,"isSkipSelf":false,"isOptional":false,"token":{"identifier":{"reference":{"__symbol":51,"members":[]}}}}],"multi":false},"module":{"reference":{"__symbol":39,"members":[]},"diDeps":[{"isAttribute":false,"isHost":false,"isSelf":false,"isSkipSelf":true,"isOptional":true,"token":{"identifier":{"reference":{"__symbol":39,"members":[]}}}}],"lifecycleHooks":[]}},{"provider":{"token":{"identifier":{"reference":{"__symbol":52,"members":[]}}},"useClass":null,"useFactory":null,"useExisting":{"identifier":{"reference":{"__symbol":49,"members":[]}}},"multi":false},"module":{"reference":{"__symbol":39,"members":[]},"diDeps":[{"isAttribute":false,"isHost":false,"isSelf":false,"isSkipSelf":true,"isOptional":true,"token":{"identifier":{"reference":{"__symbol":39,"members":[]}}}}],"lifecycleHooks":[]}},{"provider":{"token":{"identifier":{"reference":{"__symbol":53,"members":[]}}},"useClass":null,"useFactory":null,"useExisting":{"identifier":{"reference":{"__symbol":51,"members":[]}}},"multi":false},"module":{"reference":{"__symbol":39,"members":[]},"diDeps":[{"isAttribute":false,"isHost":false,"isSelf":false,"isSkipSelf":true,"isOptional":true,"token":{"identifier":{"reference":{"__symbol":39,"members":[]}}}}],"lifecycleHooks":[]}},{"provider":{"token":{"identifier":{"reference":{"__symbol":51,"members":[]},"diDeps":[{"isAttribute":false,"isHost":false,"isSelf":false,"isSkipSelf":false,"isOptional":false,"token":{"identifier":{"reference":{"__symbol":41,"members":[]}}}}],"lifecycleHooks":[1]}},"useClass":{"reference":{"__symbol":51,"members":[]},"diDeps":[{"isAttribute":false,"isHost":false,"isSelf":false,"isSkipSelf":false,"isOptional":false,"token":{"identifier":{"reference":{"__symbol":41,"members":[]}}}}],"lifecycleHooks":[1]},"useFactory":null,"deps":[{"isAttribute":false,"isHost":false,"isSelf":false,"isSkipSelf":false,"isOptional":false,"token":{"identifier":{"reference":{"__symbol":41,"members":[]}}}}],"multi":false},"module":{"reference":{"__symbol":39,"members":[]},"diDeps":[{"isAttribute":false,"isHost":false,"isSelf":false,"isSkipSelf":true,"isOptional":true,"token":{"identifier":{"reference":{"__symbol":39,"members":[]}}}}],"lifecycleHooks":[]}},{"provider":{"token":{"identifier":{"reference":{"__symbol":54,"members":[]},"diDeps":[{"isAttribute":false,"isHost":false,"isSelf":false,"isSkipSelf":false,"isOptional":false,"token":{"identifier":{"reference":{"__symbol":20,"members":[]}}}}],"lifecycleHooks":[]}},"useClass":{"reference":{"__symbol":54,"members":[]},"diDeps":[{"isAttribute":false,"isHost":false,"isSelf":false,"isSkipSelf":false,"isOptional":false,"token":{"identifier":{"reference":{"__symbol":20,"members":[]}}}}],"lifecycleHooks":[]},"useFactory":null,"deps":[{"isAttribute":false,"isHost":false,"isSelf":false,"isSkipSelf":false,"isOptional":false,"token":{"identifier":{"reference":{"__symbol":20,"members":[]}}}}],"multi":false},"module":{"reference":{"__symbol":39,"members":[]},"diDeps":[{"isAttribute":false,"isHost":false,"isSelf":false,"isSkipSelf":true,"isOptional":true,"token":{"identifier":{"reference":{"__symbol":39,"members":[]}}}}],"lifecycleHooks":[]}},{"provider":{"token":{"identifier":{"reference":{"__symbol":50,"members":[]},"diDeps":[{"isAttribute":false,"isHost":false,"isSelf":false,"isSkipSelf":false,"isOptional":false,"token":{"identifier":{"reference":{"__symbol":43,"members":[]}}}},{"isAttribute":false,"isHost":false,"isSelf":false,"isSkipSelf":false,"isOptional":false,"token":{"identifier":{"reference":{"__symbol":20,"members":[]}}}}],"lifecycleHooks":[]}},"useClass":{"reference":{"__symbol":50,"members":[]},"diDeps":[{"isAttribute":false,"isHost":false,"isSelf":false,"isSkipSelf":false,"isOptional":false,"token":{"identifier":{"reference":{"__symbol":43,"members":[]}}}},{"isAttribute":false,"isHost":false,"isSelf":false,"isSkipSelf":false,"isOptional":false,"token":{"identifier":{"reference":{"__symbol":20,"members":[]}}}}],"lifecycleHooks":[]},"useFactory":null,"deps":[{"isAttribute":false,"isHost":false,"isSelf":false,"isSkipSelf":false,"isOptional":false,"token":{"identifier":{"reference":{"__symbol":43,"members":[]}}}},{"isAttribute":false,"isHost":false,"isSelf":false,"isSkipSelf":false,"isOptional":false,"token":{"identifier":{"reference":{"__symbol":20,"members":[]}}}}],"multi":false},"module":{"reference":{"__symbol":39,"members":[]},"diDeps":[{"isAttribute":false,"isHost":false,"isSelf":false,"isSkipSelf":true,"isOptional":true,"token":{"identifier":{"reference":{"__symbol":39,"members":[]}}}}],"lifecycleHooks":[]}},{"provider":{"token":{"identifier":{"reference":{"__symbol":28,"members":[]}}},"useClass":null,"useFactory":{"reference":{"__symbol":55,"members":[]},"diDeps":[{"isAttribute":false,"isHost":false,"isSelf":false,"isSkipSelf":false,"isOptional":true,"token":{"identifier":{"reference":{"__symbol":56,"members":[]}}}},{"isAttribute":false,"isHost":false,"isSelf":false,"isSkipSelf":false,"isOptional":true,"token":{"identifier":{"reference":{"__symbol":57,"members":[]}}}}]},"deps":[{"isAttribute":false,"isHost":false,"isSelf":false,"isSkipSelf":false,"isOptional":true,"token":{"identifier":{"reference":{"__symbol":56,"members":[]}}}},{"isAttribute":false,"isHost":false,"isSelf":false,"isSkipSelf":false,"isOptional":true,"token":{"identifier":{"reference":{"__symbol":57,"members":[]}}}}],"multi":true},"module":{"reference":{"__symbol":39,"members":[]},"diDeps":[{"isAttribute":false,"isHost":false,"isSelf":false,"isSkipSelf":true,"isOptional":true,"token":{"identifier":{"reference":{"__symbol":39,"members":[]}}}}],"lifecycleHooks":[]}},{"provider":{"token":{"identifier":{"reference":{"__symbol":58,"members":[]},"diDeps":[{"isAttribute":false,"isHost":false,"isSelf":false,"isSkipSelf":false,"isOptional":false,"token":{"identifier":{"reference":{"__symbol":41,"members":[]}}}}],"lifecycleHooks":[]}},"useClass":{"reference":{"__symbol":58,"members":[]},"diDeps":[{"isAttribute":false,"isHost":false,"isSelf":false,"isSkipSelf":false,"isOptional":false,"token":{"identifier":{"reference":{"__symbol":41,"members":[]}}}}],"lifecycleHooks":[]},"useFactory":null,"deps":[{"isAttribute":false,"isHost":false,"isSelf":false,"isSkipSelf":false,"isOptional":false,"token":{"identifier":{"reference":{"__symbol":41,"members":[]}}}}],"multi":false},"module":{"reference":{"__symbol":39,"members":[]},"diDeps":[{"isAttribute":false,"isHost":false,"isSelf":false,"isSkipSelf":true,"isOptional":true,"token":{"identifier":{"reference":{"__symbol":39,"members":[]}}}}],"lifecycleHooks":[]}},{"provider":{"token":{"identifier":{"reference":{"__symbol":59,"members":[]},"diDeps":[{"isAttribute":false,"isHost":false,"isSelf":false,"isSkipSelf":false,"isOptional":false,"token":{"identifier":{"reference":{"__symbol":41,"members":[]}}}}],"lifecycleHooks":[]}},"useClass":{"reference":{"__symbol":59,"members":[]},"diDeps":[{"isAttribute":false,"isHost":false,"isSelf":false,"isSkipSelf":false,"isOptional":false,"token":{"identifier":{"reference":{"__symbol":41,"members":[]}}}}],"lifecycleHooks":[]},"useFactory":null,"deps":[{"isAttribute":false,"isHost":false,"isSelf":false,"isSkipSelf":false,"isOptional":false,"token":{"identifier":{"reference":{"__symbol":41,"members":[]}}}}],"multi":false},"module":{"reference":{"__symbol":39,"members":[]},"diDeps":[{"isAttribute":false,"isHost":false,"isSelf":false,"isSkipSelf":true,"isOptional":true,"token":{"identifier":{"reference":{"__symbol":39,"members":[]}}}}],"lifecycleHooks":[]}},{"provider":{"token":{"identifier":{"reference":{"__symbol":60,"members":[]}}},"useClass":{"reference":{"__symbol":61,"members":[]},"diDeps":[],"lifecycleHooks":[]},"useFactory":null,"deps":[],"multi":false},"module":{"reference":{"__symbol":62,"members":[]},"diDeps":[],"lifecycleHooks":[]}},{"provider":{"token":{"identifier":{"reference":{"__symbol":63,"members":[]}}},"useClass":{"reference":{"__symbol":64,"members":[]},"diDeps":[{"isAttribute":false,"isHost":false,"isSelf":false,"isSkipSelf":false,"isOptional":false,"token":{"identifier":{"reference":{"__symbol":52,"members":[]}}}}],"lifecycleHooks":[]},"useFactory":null,"deps":[{"isAttribute":false,"isHost":false,"isSelf":false,"isSkipSelf":false,"isOptional":false,"token":{"identifier":{"reference":{"__symbol":52,"members":[]}}}}],"multi":false},"module":{"reference":{"__symbol":62,"members":[]},"diDeps":[],"lifecycleHooks":[]}},{"provider":{"token":{"identifier":{"reference":{"__symbol":65,"members":[]}}},"useClass":null,"useFactory":{"reference":{"__symbol":66,"members":[]},"diDeps":[]},"deps":[],"multi":false},"module":{"reference":{"__symbol":62,"members":[]},"diDeps":[],"lifecycleHooks":[]}},{"provider":{"token":{"identifier":{"reference":{"__symbol":67,"members":[]}}},"useClass":{"reference":{"__symbol":68,"members":[]},"diDeps":[{"isAttribute":false,"isHost":false,"isSelf":false,"isSkipSelf":false,"isOptional":false,"token":{"identifier":{"reference":{"__symbol":60,"members":[]}}}},{"isAttribute":false,"isHost":false,"isSelf":false,"isSkipSelf":false,"isOptional":false,"token":{"identifier":{"reference":{"__symbol":65,"members":[]}}}}],"lifecycleHooks":[]},"useFactory":null,"deps":[{"isAttribute":false,"isHost":false,"isSelf":false,"isSkipSelf":false,"isOptional":false,"token":{"identifier":{"reference":{"__symbol":60,"members":[]}}}},{"isAttribute":false,"isHost":false,"isSelf":false,"isSkipSelf":false,"isOptional":false,"token":{"identifier":{"reference":{"__symbol":65,"members":[]}}}}],"multi":false},"module":{"reference":{"__symbol":62,"members":[]},"diDeps":[],"lifecycleHooks":[]}},{"provider":{"token":{"identifier":{"reference":{"__symbol":52,"members":[]}}},"useClass":null,"useFactory":{"reference":{"__symbol":69,"members":[]},"diDeps":[{"isAttribute":false,"isHost":false,"isSelf":false,"isSkipSelf":false,"isOptional":false,"token":{"identifier":{"reference":{"__symbol":49,"members":[]}}}},{"isAttribute":false,"isHost":false,"isSelf":false,"isSkipSelf":false,"isOptional":false,"token":{"identifier":{"reference":{"__symbol":67,"members":[]}}}},{"isAttribute":false,"isHost":false,"isSelf":false,"isSkipSelf":false,"isOptional":false,"token":{"identifier":{"reference":{"__symbol":20,"members":[]}}}}]},"deps":[{"isAttribute":false,"isHost":false,"isSelf":false,"isSkipSelf":false,"isOptional":false,"token":{"identifier":{"reference":{"__symbol":49,"members":[]}}}},{"isAttribute":false,"isHost":false,"isSelf":false,"isSkipSelf":false,"isOptional":false,"token":{"identifier":{"reference":{"__symbol":67,"members":[]}}}},{"isAttribute":false,"isHost":false,"isSelf":false,"isSkipSelf":false,"isOptional":false,"token":{"identifier":{"reference":{"__symbol":20,"members":[]}}}}],"multi":false},"module":{"reference":{"__symbol":62,"members":[]},"diDeps":[],"lifecycleHooks":[]}},{"provider":{"token":{"identifier":{"reference":{"__symbol":70,"members":[]},"diDeps":[{"isAttribute":false,"isHost":false,"isSelf":false,"isSkipSelf":false,"isOptional":false,"token":{"identifier":{"reference":{"__symbol":20,"members":[]}}}},{"isAttribute":false,"isHost":false,"isSelf":false,"isSkipSelf":false,"isOptional":false,"token":{"identifier":{"reference":{"__symbol":41,"members":[]}}}},{"isAttribute":false,"isHost":false,"isSelf":false,"isSkipSelf":false,"isOptional":false,"token":{"identifier":{"reference":{"__symbol":53,"members":[]}}}}],"lifecycleHooks":[]}},"useClass":{"reference":{"__symbol":70,"members":[]},"diDeps":[{"isAttribute":false,"isHost":false,"isSelf":false,"isSkipSelf":false,"isOptional":false,"token":{"identifier":{"reference":{"__symbol":20,"members":[]}}}},{"isAttribute":false,"isHost":false,"isSelf":false,"isSkipSelf":false,"isOptional":false,"token":{"identifier":{"reference":{"__symbol":41,"members":[]}}}},{"isAttribute":false,"isHost":false,"isSelf":false,"isSkipSelf":false,"isOptional":false,"token":{"identifier":{"reference":{"__symbol":53,"members":[]}}}}],"lifecycleHooks":[]},"useFactory":null,"deps":[{"isAttribute":false,"isHost":false,"isSelf":false,"isSkipSelf":false,"isOptional":false,"token":{"identifier":{"reference":{"__symbol":20,"members":[]}}}},{"isAttribute":false,"isHost":false,"isSelf":false,"isSkipSelf":false,"isOptional":false,"token":{"identifier":{"reference":{"__symbol":41,"members":[]}}}},{"isAttribute":false,"isHost":false,"isSelf":false,"isSkipSelf":false,"isOptional":false,"token":{"identifier":{"reference":{"__symbol":53,"members":[]}}}}],"multi":false},"module":{"reference":{"__symbol":71,"members":[]},"diDeps":[],"lifecycleHooks":[]}},{"provider":{"token":{"identifier":{"reference":{"__symbol":52,"members":[]}}},"useClass":null,"useFactory":{"reference":{"__symbol":72,"members":[]},"diDeps":[{"isAttribute":false,"isHost":false,"isSelf":false,"isSkipSelf":false,"isOptional":false,"token":{"identifier":{"reference":{"__symbol":70,"members":[]}}}},{"isAttribute":false,"isHost":false,"isSelf":false,"isSkipSelf":false,"isOptional":false,"token":{"identifier":{"reference":{"__symbol":67,"members":[]}}}},{"isAttribute":false,"isHost":false,"isSelf":false,"isSkipSelf":false,"isOptional":false,"token":{"identifier":{"reference":{"__symbol":20,"members":[]}}}}]},"deps":[{"isAttribute":false,"isHost":false,"isSelf":false,"isSkipSelf":false,"isOptional":false,"token":{"identifier":{"reference":{"__symbol":70,"members":[]}}}},{"isAttribute":false,"isHost":false,"isSelf":false,"isSkipSelf":false,"isOptional":false,"token":{"identifier":{"reference":{"__symbol":67,"members":[]}}}},{"isAttribute":false,"isHost":false,"isSelf":false,"isSkipSelf":false,"isOptional":false,"token":{"identifier":{"reference":{"__symbol":20,"members":[]}}}}],"multi":false},"module":{"reference":{"__symbol":71,"members":[]},"diDeps":[],"lifecycleHooks":[]}},{"provider":{"token":{"identifier":{"reference":{"__symbol":73,"members":[]},"diDeps":[{"isAttribute":false,"isHost":false,"isSelf":false,"isSkipSelf":false,"isOptional":false,"token":{"identifier":{"reference":{"__symbol":41,"members":[]}}}},{"isAttribute":false,"isHost":false,"isSelf":false,"isSkipSelf":false,"isOptional":true,"token":{"identifier":{"reference":{"__symbol":74,"members":[]}}}}],"lifecycleHooks":[]}},"useClass":{"reference":{"__symbol":73,"members":[]},"diDeps":[{"isAttribute":false,"isHost":false,"isSelf":false,"isSkipSelf":false,"isOptional":false,"token":{"identifier":{"reference":{"__symbol":41,"members":[]}}}},{"isAttribute":false,"isHost":false,"isSelf":false,"isSkipSelf":false,"isOptional":true,"token":{"identifier":{"reference":{"__symbol":74,"members":[]}}}}],"lifecycleHooks":[]},"useFactory":null,"deps":[{"isAttribute":false,"isHost":false,"isSelf":false,"isSkipSelf":false,"isOptional":false,"token":{"identifier":{"reference":{"__symbol":41,"members":[]}}}},{"isAttribute":false,"isHost":false,"isSelf":false,"isSkipSelf":false,"isOptional":true,"token":{"identifier":{"reference":{"__symbol":74,"members":[]}}}}],"multi":false},"module":{"reference":{"__symbol":71,"members":[]},"diDeps":[],"lifecycleHooks":[]}},{"provider":{"token":{"identifier":{"reference":{"__symbol":53,"members":[]}}},"useClass":null,"useFactory":null,"useExisting":{"identifier":{"reference":{"__symbol":73,"members":[]}}},"multi":false},"module":{"reference":{"__symbol":71,"members":[]},"diDeps":[],"lifecycleHooks":[]}},{"provider":{"token":{"identifier":{"reference":{"__symbol":4,"members":[]}}},"useClass":null,"useFactory":{"reference":{"__symbol":75,"members":[]},"diDeps":[{"isAttribute":false,"isHost":false,"isSelf":false,"isSkipSelf":false,"isOptional":false,"token":{"identifier":{"reference":{"__symbol":6,"members":[]}}}},{"isAttribute":false,"isHost":false,"isSelf":false,"isSkipSelf":false,"isOptional":false,"token":{"identifier":{"reference":{"__symbol":7,"members":[]}}}}]},"deps":[{"isAttribute":false,"isHost":false,"isSelf":false,"isSkipSelf":false,"isOptional":false,"token":{"identifier":{"reference":{"__symbol":6,"members":[]}}}},{"isAttribute":false,"isHost":false,"isSelf":false,"isSkipSelf":false,"isOptional":false,"token":{"identifier":{"reference":{"__symbol":7,"members":[]}}}}],"multi":false},"module":{"reference":{"__symbol":71,"members":[]},"diDeps":[],"lifecycleHooks":[]}},{"provider":{"token":{"identifier":{"reference":{"__symbol":9,"members":[]}}},"useClass":{"reference":{"__symbol":76,"members":[]},"diDeps":[],"lifecycleHooks":[]},"useFactory":null,"deps":[],"multi":false},"module":{"reference":{"__symbol":71,"members":[]},"diDeps":[],"lifecycleHooks":[]}},{"provider":{"token":{"identifier":{"reference":{"__symbol":13,"members":[]}}},"useClass":{"reference":{"__symbol":77,"members":[]},"diDeps":[],"lifecycleHooks":[]},"useFactory":null,"deps":[],"multi":false},"module":{"reference":{"__symbol":71,"members":[]},"diDeps":[],"lifecycleHooks":[]}},{"provider":{"token":{"identifier":{"reference":{"__symbol":54,"members":[]}}},"useClass":null,"useValue":null,"useFactory":null,"multi":false},"module":{"reference":{"__symbol":71,"members":[]},"diDeps":[],"lifecycleHooks":[]}},{"provider":{"token":{"identifier":{"reference":{"__symbol":78,"members":[]}}},"useClass":{"reference":{"__symbol":79,"members":[]},"diDeps":[{"isAttribute":false,"isHost":false,"isSelf":false,"isSkipSelf":false,"isOptional":false,"token":{"identifier":{"reference":{"__symbol":80,"members":[]}}}},{"isAttribute":false,"isHost":false,"isSelf":false,"isSkipSelf":false,"isOptional":false,"token":{"identifier":{"reference":{"__symbol":52,"members":[]}}}}],"lifecycleHooks":[]},"useFactory":null,"deps":[{"isAttribute":false,"isHost":false,"isSelf":false,"isSkipSelf":false,"isOptional":false,"token":{"identifier":{"reference":{"__symbol":80,"members":[]}}}},{"isAttribute":false,"isHost":false,"isSelf":false,"isSkipSelf":false,"isOptional":false,"token":{"identifier":{"reference":{"__symbol":52,"members":[]}}}}],"multi":false},"module":{"reference":{"__symbol":81,"members":[]},"diDeps":[],"lifecycleHooks":[]}},{"provider":{"token":{"identifier":{"reference":{"__symbol":82,"members":[]},"diDeps":[{"isAttribute":false,"isHost":false,"isSelf":false,"isSkipSelf":false,"isOptional":false,"token":{"identifier":{"reference":{"__symbol":4,"members":[]}}}},{"isAttribute":false,"isHost":false,"isSelf":false,"isSkipSelf":false,"isOptional":false,"token":{"identifier":{"reference":{"__symbol":78,"members":[]}}}}],"lifecycleHooks":[]}},"useClass":{"reference":{"__symbol":82,"members":[]},"diDeps":[{"isAttribute":false,"isHost":false,"isSelf":false,"isSkipSelf":false,"isOptional":false,"token":{"identifier":{"reference":{"__symbol":4,"members":[]}}}},{"isAttribute":false,"isHost":false,"isSelf":false,"isSkipSelf":false,"isOptional":false,"token":{"identifier":{"reference":{"__symbol":78,"members":[]}}}}],"lifecycleHooks":[]},"useFactory":null,"deps":[{"isAttribute":false,"isHost":false,"isSelf":false,"isSkipSelf":false,"isOptional":false,"token":{"identifier":{"reference":{"__symbol":4,"members":[]}}}},{"isAttribute":false,"isHost":false,"isSelf":false,"isSkipSelf":false,"isOptional":false,"token":{"identifier":{"reference":{"__symbol":78,"members":[]}}}}],"multi":false},"module":{"reference":{"__symbol":83,"members":[]},"diDeps":[],"lifecycleHooks":[]}},{"provider":{"token":{"identifier":{"reference":{"__symbol":84,"members":[]},"diDeps":[],"lifecycleHooks":[]}},"useClass":{"reference":{"__symbol":84,"members":[]},"diDeps":[],"lifecycleHooks":[]},"useFactory":null,"deps":[],"multi":false},"module":{"reference":{"__symbol":85,"members":[]},"diDeps":[],"lifecycleHooks":[]}},{"provider":{"token":{"identifier":{"reference":{"__symbol":86,"members":[]},"diDeps":[{"isAttribute":false,"isHost":false,"isSelf":false,"isSkipSelf":false,"isOptional":false,"token":{"identifier":{"reference":{"__symbol":82,"members":[]}}}}],"lifecycleHooks":[]}},"useClass":{"reference":{"__symbol":86,"members":[]},"diDeps":[{"isAttribute":false,"isHost":false,"isSelf":false,"isSkipSelf":false,"isOptional":false,"token":{"identifier":{"reference":{"__symbol":82,"members":[]}}}}],"lifecycleHooks":[]},"useFactory":null,"deps":[{"isAttribute":false,"isHost":false,"isSelf":false,"isSkipSelf":false,"isOptional":false,"token":{"identifier":{"reference":{"__symbol":82,"members":[]}}}}],"multi":false},"module":{"reference":{"__symbol":85,"members":[]},"diDeps":[],"lifecycleHooks":[]}},{"provider":{"token":{"identifier":{"reference":{"__symbol":30,"members":[]}}},"useClass":null,"useValue":"ng-universal-example","useFactory":null,"multi":false},"module":{"reference":{"__symbol":1,"members":[]},"diDeps":[],"lifecycleHooks":[]}},{"provider":{"token":{"identifier":{"reference":{"__symbol":74,"members":[]}}},"useClass":null,"useFactory":null,"useExisting":{"identifier":{"reference":{"__symbol":30,"members":[]}}},"multi":false},"module":{"reference":{"__symbol":1,"members":[]},"diDeps":[],"lifecycleHooks":[]}},{"provider":{"token":{"identifier":{"reference":{"__symbol":28,"members":[]}}},"useClass":null,"useFactory":{"reference":{"__symbol":87,"members":[]},"diDeps":[{"isAttribute":false,"isHost":false,"isSelf":false,"isSkipSelf":false,"isOptional":false,"token":{"identifier":{"reference":{"__symbol":74,"members":[]}}}},{"isAttribute":false,"isHost":false,"isSelf":false,"isSkipSelf":false,"isOptional":false,"token":{"identifier":{"reference":{"__symbol":41,"members":[]}}}},{"isAttribute":false,"isHost":false,"isSelf":false,"isSkipSelf":false,"isOptional":false,"token":{"identifier":{"reference":{"__symbol":22,"members":[]}}}}]},"deps":[{"isAttribute":false,"isHost":false,"isSelf":false,"isSkipSelf":false,"isOptional":false,"token":{"identifier":{"reference":{"__symbol":74,"members":[]}}}},{"isAttribute":false,"isHost":false,"isSelf":false,"isSkipSelf":false,"isOptional":false,"token":{"identifier":{"reference":{"__symbol":41,"members":[]}}}},{"isAttribute":false,"isHost":false,"isSelf":false,"isSkipSelf":false,"isOptional":false,"token":{"identifier":{"reference":{"__symbol":22,"members":[]}}}}],"multi":true},"module":{"reference":{"__symbol":1,"members":[]},"diDeps":[],"lifecycleHooks":[]}},{"provider":{"token":{"identifier":{"reference":{"__symbol":88,"members":[]}}},"useClass":null,"useFactory":{"reference":{"__symbol":0,"members":[]},"diDeps":[{"isAttribute":false,"isHost":false,"isSelf":false,"isSkipSelf":false,"isOptional":false,"token":{"identifier":{"reference":{"__symbol":27,"members":[]}}}},{"isAttribute":false,"isHost":false,"isSelf":false,"isSkipSelf":false,"isOptional":false,"token":{"identifier":{"reference":{"__symbol":78,"members":[]}}}}]},"deps":[{"isAttribute":false,"isHost":false,"isSelf":false,"isSkipSelf":false,"isOptional":false,"token":{"identifier":{"reference":{"__symbol":27,"members":[]}}}},{"isAttribute":false,"isHost":false,"isSelf":false,"isSkipSelf":false,"isOptional":false,"token":{"identifier":{"reference":{"__symbol":78,"members":[]}}}}],"multi":true},"module":{"reference":{"__symbol":1,"members":[]},"diDeps":[],"lifecycleHooks":[]}}],"modules":[{"reference":{"__symbol":8,"members":[]},"diDeps":[],"lifecycleHooks":[]},{"reference":{"__symbol":18,"members":[]},"diDeps":[],"lifecycleHooks":[]},{"reference":{"__symbol":26,"members":[]},"diDeps":[{"isAttribute":false,"isHost":false,"isSelf":false,"isSkipSelf":false,"isOptional":false,"token":{"identifier":{"reference":{"__symbol":27,"members":[]}}}}],"lifecycleHooks":[]},{"reference":{"__symbol":39,"members":[]},"diDeps":[{"isAttribute":false,"isHost":false,"isSelf":false,"isSkipSelf":true,"isOptional":true,"token":{"identifier":{"reference":{"__symbol":39,"members":[]}}}}],"lifecycleHooks":[]},{"reference":{"__symbol":62,"members":[]},"diDeps":[],"lifecycleHooks":[]},{"reference":{"__symbol":71,"members":[]},"diDeps":[],"lifecycleHooks":[]},{"reference":{"__symbol":81,"members":[]},"diDeps":[],"lifecycleHooks":[]},{"reference":{"__symbol":83,"members":[]},"diDeps":[],"lifecycleHooks":[]},{"reference":{"__symbol":85,"members":[]},"diDeps":[],"lifecycleHooks":[]},{"reference":{"__symbol":1,"members":[]},"diDeps":[],"lifecycleHooks":[]}],"exportedDirectives":[],"exportedPipes":[]}}],"symbols":[{"__symbol":0,"name":"onBootstrap","filePath":"/Users/elysekolker/dev/personal/chapter-12-frameworks/angular2/src/app.server.module.d.ts"},{"__symbol":1,"name":"AppServerModule","filePath":"/Users/elysekolker/dev/personal/chapter-12-frameworks/angular2/src/app.server.module.d.ts"},{"__symbol":2,"name":"AppComponent","filePath":"/Users/elysekolker/dev/personal/chapter-12-frameworks/angular2/src/app/app.component.d.ts"},{"__symbol":3,"name":"AppComponentNgFactory","filePath":"/Users/elysekolker/dev/personal/chapter-12-frameworks/angular2/src/app/app.component.ngfactory.d.ts"},{"__symbol":4,"name":"Http","filePath":"/Users/elysekolker/dev/personal/chapter-12-frameworks/angular2/node_modules/@angular/http/http.d.ts"},{"__symbol":5,"name":"ɵc","filePath":"/Users/elysekolker/dev/personal/chapter-12-frameworks/angular2/node_modules/@angular/http/http.d.ts"},{"__symbol":6,"name":"XHRBackend","filePath":"/Users/elysekolker/dev/personal/chapter-12-frameworks/angular2/node_modules/@angular/http/http.d.ts"},{"__symbol":7,"name":"RequestOptions","filePath":"/Users/elysekolker/dev/personal/chapter-12-frameworks/angular2/node_modules/@angular/http/http.d.ts"},{"__symbol":8,"name":"HttpModule","filePath":"/Users/elysekolker/dev/personal/chapter-12-frameworks/angular2/node_modules/@angular/http/http.d.ts"},{"__symbol":9,"name":"BrowserXhr","filePath":"/Users/elysekolker/dev/personal/chapter-12-frameworks/angular2/node_modules/@angular/http/http.d.ts"},{"__symbol":10,"name":"BaseRequestOptions","filePath":"/Users/elysekolker/dev/personal/chapter-12-frameworks/angular2/node_modules/@angular/http/http.d.ts"},{"__symbol":11,"name":"ResponseOptions","filePath":"/Users/elysekolker/dev/personal/chapter-12-frameworks/angular2/node_modules/@angular/http/http.d.ts"},{"__symbol":12,"name":"BaseResponseOptions","filePath":"/Users/elysekolker/dev/personal/chapter-12-frameworks/angular2/node_modules/@angular/http/http.d.ts"},{"__symbol":13,"name":"XSRFStrategy","filePath":"/Users/elysekolker/dev/personal/chapter-12-frameworks/angular2/node_modules/@angular/http/http.d.ts"},{"__symbol":14,"name":"ɵb","filePath":"/Users/elysekolker/dev/personal/chapter-12-frameworks/angular2/node_modules/@angular/http/http.d.ts"},{"__symbol":15,"name":"NgLocalization","filePath":"/Users/elysekolker/dev/personal/chapter-12-frameworks/angular2/node_modules/@angular/common/common.d.ts"},{"__symbol":16,"name":"NgLocaleLocalization","filePath":"/Users/elysekolker/dev/personal/chapter-12-frameworks/angular2/node_modules/@angular/common/common.d.ts"},{"__symbol":17,"name":"LOCALE_ID","filePath":"/Users/elysekolker/dev/personal/chapter-12-frameworks/angular2/node_modules/@angular/core/core.d.ts"},{"__symbol":18,"name":"CommonModule","filePath":"/Users/elysekolker/dev/personal/chapter-12-frameworks/angular2/node_modules/@angular/common/common.d.ts"},{"__symbol":19,"name":"ɵe","filePath":"/Users/elysekolker/dev/personal/chapter-12-frameworks/angular2/node_modules/@angular/core/core.d.ts"},{"__symbol":20,"name":"NgZone","filePath":"/Users/elysekolker/dev/personal/chapter-12-frameworks/angular2/node_modules/@angular/core/core.d.ts"},{"__symbol":21,"name":"ɵConsole","filePath":"/Users/elysekolker/dev/personal/chapter-12-frameworks/angular2/node_modules/@angular/core/core.d.ts"},{"__symbol":22,"name":"Injector","filePath":"/Users/elysekolker/dev/personal/chapter-12-frameworks/angular2/node_modules/@angular/core/core.d.ts"},{"__symbol":23,"name":"ErrorHandler","filePath":"/Users/elysekolker/dev/personal/chapter-12-frameworks/angular2/node_modules/@angular/core/core.d.ts"},{"__symbol":24,"name":"ComponentFactoryResolver","filePath":"/Users/elysekolker/dev/personal/chapter-12-frameworks/angular2/node_modules/@angular/core/core.d.ts"},{"__symbol":25,"name":"ApplicationInitStatus","filePath":"/Users/elysekolker/dev/personal/chapter-12-frameworks/angular2/node_modules/@angular/core/core.d.ts"},{"__symbol":26,"name":"ApplicationModule","filePath":"/Users/elysekolker/dev/personal/chapter-12-frameworks/angular2/node_modules/@angular/core/core.d.ts"},{"__symbol":27,"name":"ApplicationRef","filePath":"/Users/elysekolker/dev/personal/chapter-12-frameworks/angular2/node_modules/@angular/core/core.d.ts"},{"__symbol":28,"name":"APP_INITIALIZER","filePath":"/Users/elysekolker/dev/personal/chapter-12-frameworks/angular2/node_modules/@angular/core/core.d.ts"},{"__symbol":29,"name":"Compiler","filePath":"/Users/elysekolker/dev/personal/chapter-12-frameworks/angular2/node_modules/@angular/core/core.d.ts"},{"__symbol":30,"name":"APP_ID","filePath":"/Users/elysekolker/dev/personal/chapter-12-frameworks/angular2/node_modules/@angular/core/core.d.ts"},{"__symbol":31,"name":"ɵf","filePath":"/Users/elysekolker/dev/personal/chapter-12-frameworks/angular2/node_modules/@angular/core/core.d.ts"},{"__symbol":32,"name":"IterableDiffers","filePath":"/Users/elysekolker/dev/personal/chapter-12-frameworks/angular2/node_modules/@angular/core/core.d.ts"},{"__symbol":33,"name":"ɵk","filePath":"/Users/elysekolker/dev/personal/chapter-12-frameworks/angular2/node_modules/@angular/core/core.d.ts"},{"__symbol":34,"name":"KeyValueDiffers","filePath":"/Users/elysekolker/dev/personal/chapter-12-frameworks/angular2/node_modules/@angular/core/core.d.ts"},{"__symbol":35,"name":"ɵl","filePath":"/Users/elysekolker/dev/personal/chapter-12-frameworks/angular2/node_modules/@angular/core/core.d.ts"},{"__symbol":36,"name":"ɵm","filePath":"/Users/elysekolker/dev/personal/chapter-12-frameworks/angular2/node_modules/@angular/core/core.d.ts"},{"__symbol":37,"name":"Sanitizer","filePath":"/Users/elysekolker/dev/personal/chapter-12-frameworks/angular2/node_modules/@angular/core/core.d.ts"},{"__symbol":38,"name":"DomSanitizer","filePath":"/Users/elysekolker/dev/personal/chapter-12-frameworks/angular2/node_modules/@angular/platform-browser/platform-browser.d.ts"},{"__symbol":39,"name":"BrowserModule","filePath":"/Users/elysekolker/dev/personal/chapter-12-frameworks/angular2/node_modules/@angular/platform-browser/platform-browser.d.ts"},{"__symbol":40,"name":"ɵe","filePath":"/Users/elysekolker/dev/personal/chapter-12-frameworks/angular2/node_modules/@angular/platform-browser/platform-browser.d.ts"},{"__symbol":41,"name":"DOCUMENT","filePath":"/Users/elysekolker/dev/personal/chapter-12-frameworks/angular2/node_modules/@angular/platform-browser/platform-browser.d.ts"},{"__symbol":42,"name":"ɵa","filePath":"/Users/elysekolker/dev/personal/chapter-12-frameworks/angular2/node_modules/@angular/platform-browser/platform-browser.d.ts"},{"__symbol":43,"name":"EVENT_MANAGER_PLUGINS","filePath":"/Users/elysekolker/dev/personal/chapter-12-frameworks/angular2/node_modules/@angular/platform-browser/platform-browser.d.ts"},{"__symbol":44,"name":"ɵDomEventsPlugin","filePath":"/Users/elysekolker/dev/personal/chapter-12-frameworks/angular2/node_modules/@angular/platform-browser/platform-browser.d.ts"},{"__symbol":45,"name":"ɵKeyEventsPlugin","filePath":"/Users/elysekolker/dev/personal/chapter-12-frameworks/angular2/node_modules/@angular/platform-browser/platform-browser.d.ts"},{"__symbol":46,"name":"ɵHammerGesturesPlugin","filePath":"/Users/elysekolker/dev/personal/chapter-12-frameworks/angular2/node_modules/@angular/platform-browser/platform-browser.d.ts"},{"__symbol":47,"name":"HAMMER_GESTURE_CONFIG","filePath":"/Users/elysekolker/dev/personal/chapter-12-frameworks/angular2/node_modules/@angular/platform-browser/platform-browser.d.ts"},{"__symbol":48,"name":"HammerGestureConfig","filePath":"/Users/elysekolker/dev/personal/chapter-12-frameworks/angular2/node_modules/@angular/platform-browser/platform-browser.d.ts"},{"__symbol":49,"name":"ɵDomRendererFactory2","filePath":"/Users/elysekolker/dev/personal/chapter-12-frameworks/angular2/node_modules/@angular/platform-browser/platform-browser.d.ts"},{"__symbol":50,"name":"EventManager","filePath":"/Users/elysekolker/dev/personal/chapter-12-frameworks/angular2/node_modules/@angular/platform-browser/platform-browser.d.ts"},{"__symbol":51,"name":"ɵDomSharedStylesHost","filePath":"/Users/elysekolker/dev/personal/chapter-12-frameworks/angular2/node_modules/@angular/platform-browser/platform-browser.d.ts"},{"__symbol":52,"name":"RendererFactory2","filePath":"/Users/elysekolker/dev/personal/chapter-12-frameworks/angular2/node_modules/@angular/core/core.d.ts"},{"__symbol":53,"name":"ɵSharedStylesHost","filePath":"/Users/elysekolker/dev/personal/chapter-12-frameworks/angular2/node_modules/@angular/platform-browser/platform-browser.d.ts"},{"__symbol":54,"name":"Testability","filePath":"/Users/elysekolker/dev/personal/chapter-12-frameworks/angular2/node_modules/@angular/core/core.d.ts"},{"__symbol":55,"name":"ɵc","filePath":"/Users/elysekolker/dev/personal/chapter-12-frameworks/angular2/node_modules/@angular/platform-browser/platform-browser.d.ts"},{"__symbol":56,"name":"NgProbeToken","filePath":"/Users/elysekolker/dev/personal/chapter-12-frameworks/angular2/node_modules/@angular/platform-browser/platform-browser.d.ts"},{"__symbol":57,"name":"NgProbeToken","filePath":"/Users/elysekolker/dev/personal/chapter-12-frameworks/angular2/node_modules/@angular/core/core.d.ts"},{"__symbol":58,"name":"Meta","filePath":"/Users/elysekolker/dev/personal/chapter-12-frameworks/angular2/node_modules/@angular/platform-browser/platform-browser.d.ts"},{"__symbol":59,"name":"Title","filePath":"/Users/elysekolker/dev/personal/chapter-12-frameworks/angular2/node_modules/@angular/platform-browser/platform-browser.d.ts"},{"__symbol":60,"name":"AnimationDriver","filePath":"/Users/elysekolker/dev/personal/chapter-12-frameworks/angular2/node_modules/@angular/animations/browser/index.d.ts"},{"__symbol":61,"name":"ɵNoopAnimationDriver","filePath":"/Users/elysekolker/dev/personal/chapter-12-frameworks/angular2/node_modules/@angular/animations/browser/index.d.ts"},{"__symbol":62,"name":"NoopAnimationsModule","filePath":"/Users/elysekolker/dev/personal/chapter-12-frameworks/angular2/node_modules/@angular/platform-browser/animations/index.d.ts"},{"__symbol":63,"name":"AnimationBuilder","filePath":"/Users/elysekolker/dev/personal/chapter-12-frameworks/angular2/node_modules/@angular/animations/animations.d.ts"},{"__symbol":64,"name":"ɵBrowserAnimationBuilder","filePath":"/Users/elysekolker/dev/personal/chapter-12-frameworks/angular2/node_modules/@angular/platform-browser/animations/index.d.ts"},{"__symbol":65,"name":"ɵAnimationStyleNormalizer","filePath":"/Users/elysekolker/dev/personal/chapter-12-frameworks/angular2/node_modules/@angular/animations/browser/index.d.ts"},{"__symbol":66,"name":"ɵd","filePath":"/Users/elysekolker/dev/personal/chapter-12-frameworks/angular2/node_modules/@angular/platform-browser/animations/index.d.ts"},{"__symbol":67,"name":"ɵAnimationEngine","filePath":"/Users/elysekolker/dev/personal/chapter-12-frameworks/angular2/node_modules/@angular/animations/browser/index.d.ts"},{"__symbol":68,"name":"ɵb","filePath":"/Users/elysekolker/dev/personal/chapter-12-frameworks/angular2/node_modules/@angular/platform-browser/animations/index.d.ts"},{"__symbol":69,"name":"ɵe","filePath":"/Users/elysekolker/dev/personal/chapter-12-frameworks/angular2/node_modules/@angular/platform-browser/animations/index.d.ts"},{"__symbol":70,"name":"ɵServerRendererFactory2","filePath":"/Users/elysekolker/dev/personal/chapter-12-frameworks/angular2/node_modules/@angular/platform-server/platform-server.d.ts"},{"__symbol":71,"name":"ServerModule","filePath":"/Users/elysekolker/dev/personal/chapter-12-frameworks/angular2/node_modules/@angular/platform-server/platform-server.d.ts"},{"__symbol":72,"name":"ɵa","filePath":"/Users/elysekolker/dev/personal/chapter-12-frameworks/angular2/node_modules/@angular/platform-server/platform-server.d.ts"},{"__symbol":73,"name":"ɵb","filePath":"/Users/elysekolker/dev/personal/chapter-12-frameworks/angular2/node_modules/@angular/platform-server/platform-server.d.ts"},{"__symbol":74,"name":"ɵTRANSITION_ID","filePath":"/Users/elysekolker/dev/personal/chapter-12-frameworks/angular2/node_modules/@angular/platform-browser/platform-browser.d.ts"},{"__symbol":75,"name":"ɵe","filePath":"/Users/elysekolker/dev/personal/chapter-12-frameworks/angular2/node_modules/@angular/platform-server/platform-server.d.ts"},{"__symbol":76,"name":"ɵc","filePath":"/Users/elysekolker/dev/personal/chapter-12-frameworks/angular2/node_modules/@angular/platform-server/platform-server.d.ts"},{"__symbol":77,"name":"ɵd","filePath":"/Users/elysekolker/dev/personal/chapter-12-frameworks/angular2/node_modules/@angular/platform-server/platform-server.d.ts"},{"__symbol":78,"name":"TransferState","filePath":"/Users/elysekolker/dev/personal/chapter-12-frameworks/angular2/src/modules/transfer-state/transfer-state.d.ts"},{"__symbol":79,"name":"ServerTransferState","filePath":"/Users/elysekolker/dev/personal/chapter-12-frameworks/angular2/src/modules/transfer-state/server-transfer-state.d.ts"},{"__symbol":80,"name":"PlatformState","filePath":"/Users/elysekolker/dev/personal/chapter-12-frameworks/angular2/node_modules/@angular/platform-server/platform-server.d.ts"},{"__symbol":81,"name":"ServerTransferStateModule","filePath":"/Users/elysekolker/dev/personal/chapter-12-frameworks/angular2/src/modules/transfer-state/server-transfer-state.module.d.ts"},{"__symbol":82,"name":"TransferHttp","filePath":"/Users/elysekolker/dev/personal/chapter-12-frameworks/angular2/src/modules/transfer-http/transfer-http.d.ts"},{"__symbol":83,"name":"TransferHttpModule","filePath":"/Users/elysekolker/dev/personal/chapter-12-frameworks/angular2/src/modules/transfer-http/transfer-http.module.d.ts"},{"__symbol":84,"name":"CommentsService","filePath":"/Users/elysekolker/dev/personal/chapter-12-frameworks/angular2/src/app/services/comments.service.d.ts"},{"__symbol":85,"name":"AppModule","filePath":"/Users/elysekolker/dev/personal/chapter-12-frameworks/angular2/src/app/app.module.d.ts"},{"__symbol":86,"name":"PostsService","filePath":"/Users/elysekolker/dev/personal/chapter-12-frameworks/angular2/src/app/services/posts.service.d.ts"},{"__symbol":87,"name":"ɵf","filePath":"/Users/elysekolker/dev/personal/chapter-12-frameworks/angular2/node_modules/@angular/platform-browser/platform-browser.d.ts"},{"__symbol":88,"name":"APP_BOOTSTRAP_LISTENER","filePath":"/Users/elysekolker/dev/personal/chapter-12-frameworks/angular2/node_modules/@angular/core/core.d.ts"}]}